Workbook
Name RETEICAJULIO2025: retICA7[#All]
Name Tretefjulio2025: retfuente4[#All]

Sheet Proveedores
A1: NUMERO | B1: NOMBRE | C1: NIT
A2: 1 | B2: SISCONT LIMITADA | C2: 814000143-8
A3: 2 | B3: EL CONSTRUCTOR | C3: 1124848579
A4: 3 | B4: LB GROUP SAS | C4: 900698138-8
A5: 4 | B5: COINSER LTDA | C5: 846000005-6
A6: 5 | B6: ACEROS DUVAN | C6: 1126456991

Sheet Certificado
B1: RETENCION EN LA FUENTE
B2: Nombre | C2: EL CONSTRUCTOR | D2: AÑO | E2: 2024
B4: CONCEPTO | C4: BASE GRAVABLE | D4: TARIFA | E4: VALOR RETENIDO
B5: Compras | C5: =SUMIFS(#REF!,#REF!,Certificado!$C$2,#REF!,"APLICA",#REF!,"2,50%") -> #REF! | D5: ='ret. fuente 2025 enero junio'!D2 -> 0.025 | E5: =SUMIFS(#REF!,#REF!,Certificado!$C$2,#REF!,"APLICA",#REF!,"2,50%") -> #REF!
B6: Servicios | C6: =SUMIFS(#REF!,#REF!,Certificado!$C$2,#REF!,"APLICA",#REF!,"1%") -> #REF! | D6: ='ret. fuente 2025 enero junio'!D19 -> 0.01 | E6: =SUMIFS(#REF!,#REF!,Certificado!$C$2,#REF!,"APLICA",#REF!,"1%") -> #REF!
B8: RETEICA
B10: CONCEPTO | C10: BASE GRAVABLE | D10: TARIFA | E10: VALOR RETENIDO
B11: Compras | C11: =SUMIFS(#REF!,#REF!,Certificado!$C$2,#REF!,"APLICA",#REF!,"0,50%") -> #REF! | D11: ='ret. ICA 2025 enero junio'!D2 -> 0.006 | E11: =SUMIFS(#REF!,#REF!,Certificado!$C$2,#REF!,"APLICA",#REF!,"0,50%") -> #REF!
B12: Servicios | C12: =SUMIFS(#REF!,#REF!,Certificado!$C$2,#REF!,"APLICA",#REF!,"1%") -> #REF! | D12: ='ret. ICA 2025 enero junio'!D3 -> 0.01 | E12: =SUMIFS(#REF!,#REF!,Certificado!$C$2,#REF!,"APLICA",#REF!,"1%") -> #REF!
G14: CHEQUEO
E15: =SUM(E12+E11+E6+E5) -> #REF! | G15: =#REF! -> #REF!

Sheet ret. fuente 2025 JULIO 
A1: conceptos de retención | B1: Base mínima en UVT | C1: Base mínima en pesos | D1: Tarifa de retención. | F1: VALOR UVT
A2: Compras generales (declarantes) | B2: 27 | C2: 498000 | D2: 0.025 | F2: 49799
A3: Compras generales (no declarantes) | B3: 27 | C3: 498000 | D3: 0.035
A4: Compras con tarjeta débito o crédito | B4: 0 | C4: =retfuente4[[#This Row],[Base mínima en UVT]]*$F$2 -> 0 | D4: 0.015
A5: Compras de bienes o productos agrícolas o pecuarios sin procesamiento industrial | B5: 92 | C5: =retfuente4[[#This Row],[Base mínima en UVT]]*$F$2 -> 4581508 | D5: 0.015
A6: Compras de bienes o productos agrícolas o pecuarios con procesamiento industrial (declarantes) | B6: 27 | C6: =retfuente4[[#This Row],[Base mínima en UVT]]*$F$2 -> 1344573 | D6: 0.025
A7: Compras de bienes o productos agrícolas o pecuarios con procesamiento industrial declarantes (no declarantes) | B7: 27 | C7: =retfuente4[[#This Row],[Base mínima en UVT]]*$F$2 -> 1344573 | D7: 0.035
A8: Compras de café pergamino o cereza | B8: 160 | C8: =retfuente4[[#This Row],[Base mínima en UVT]]*$F$2 -> 7967840 | D8: 0.005
A9: Compras de combustibles derivados del petróleo | B9: 0 | C9: =retfuente4[[#This Row],[Base mínima en UVT]]*$F$2 -> 0 | D9: 0.001
A10: Enajenación de activos fijos de personas naturales (notarías y tránsito son agentes retenedores) | B10: 0 | C10: =retfuente4[[#This Row],[Base mínima en UVT]]*$F$2 -> 0 | D10: 0.01
A11: Compras de vehículos | B11: 0 | C11: =retfuente4[[#This Row],[Base mínima en UVT]]*$F$2 -> 0 | D11: 0.01
A12: Compras de bienes raíces cuya destinación y uso sea vivienda de habitación (por las primeras 20.000 UVT, es decir hasta $941.300.000) | B12: 0 | C12: =retfuente4[[#This Row],[Base mínima en UVT]]*$F$2 -> 0 | D12: 0.01
A13: Compras de bienes raíces cuya destinación y uso sea vivienda de habitación (exceso de las primeras 20.000 UVT, es decir superior a $941.300.000) | B13: 20000 | C13: =retfuente4[[#This Row],[Base mínima en UVT]]*$F$2 -> 995980000 | D13: 0.025
A14: Compras de bienes raíces cuya destinación y uso sea distinto a vivienda de habitación | B14: 0 | C14: =retfuente4[[#This Row],[Base mínima en UVT]]*$F$2 -> 0 | D14: 0.025
A15: Servicios generales (declarantes) | B15: 4 | C15: 100000 | D15: 0.04
A16: Servicios generales (no declarantes) | B16: 4 | C16: 100000 | D16: 0.06
A17: Por emolumentos eclesiásticos (declarantes) | B17: 27 | C17: =retfuente4[[#This Row],[Base mínima en UVT]]*$F$2 -> 1344573 | D17: 0.04
A18: Por emolumentos eclesiásticos (no declarantes) | B18: 27 | C18: =retfuente4[[#This Row],[Base mínima en UVT]]*$F$2 -> 1344573 | D18: 0.035
A19: Servicios de transporte de carga | B19: 4 | C19: =retfuente4[[#This Row],[Base mínima en UVT]]*$F$2 -> 199196 | D19: 0.01
A20: Servicios de transporte nacional de pasajeros por vía terrestre (declarantes) | B20: 27 | C20: =retfuente4[[#This Row],[Base mínima en UVT]]*$F$2 -> 1344573 | D20: 0.035
A21: Servicios de transporte nacional de pasajeros por vía terrestre (no declarantes) | B21: 27 | C21: =retfuente4[[#This Row],[Base mínima en UVT]]*$F$2 -> 1344573 | D21: 0.035
A22: Servicios de transporte nacional de pasajeros por vía aérea o marítima | B22: 4 | C22: =retfuente4[[#This Row],[Base mínima en UVT]]*$F$2 -> 199196 | D22: 0.01
A23: Servicios prestados por empresas de servicios temporales (sobre AIU) | B23: 4 | C23: =retfuente4[[#This Row],[Base mínima en UVT]]*$F$2 -> 199196 | D23: 0.01
A24: Servicios prestados por empresas de vigilancia y aseo (sobre AIU) | B24: 4 | C24: =retfuente4[[#This Row],[Base mínima en UVT]]*$F$2 -> 199196 | D24: 0.02
A25: Servicios integrales de salud prestados por IPS | B25: 4 | C25: =retfuente4[[#This Row],[Base mínima en UVT]]*$F$2 -> 199196 | D25: 0.02
A26: Servicios de hoteles y restaurantes (declarantes) | B26: 4 | C26: =retfuente4[[#This Row],[Base mínima en UVT]]*$F$2 -> 199196 | D26: 0.035
A27: Servicios de hoteles y restaurantes (no declarantes) | B27: 4 | C27: =retfuente4[[#This Row],[Base mínima en UVT]]*$F$2 -> 199196 | D27: 0.035
A28: Arrendamiento de bienes muebles | B28: 0 | C28: =retfuente4[[#This Row],[Base mínima en UVT]]*$F$2 -> 0 | D28: 0.04
... A43: Retención en la fuente por Iva en compras | B43: 27 | C43: =retfuente4[[#This Row],[Base mínima en UVT]]*$F$2 -> 1344573 | D43: 0.15
A44: RETENCIÓN POR PAGOS AL EXTERIOR
A45: Pagos o abonos en cuenta por concepto de intereses, comisiones, honorarios, regalías, arrendamientos, compensaciones por servicios personales, o explotación de toda especie de propiedad industrial o del know-how, prestación de servicios, beneficios o regalías provenientes de la propiedad literaria, artística y científica, explotación de películas cinematográficas y explotación de software. | B45: 0 | C45: =retfuente4[[#This Row],[Base mínima en UVT]]*$F$2 -> 0 | D45: 0.2
A46: Pagos o abonos en cuenta por concepto de consultorías, servicios técnicos y de asistencia técnica, prestados por personas no residentes o no domiciliadas en Colombia, | B46: 0 | C46: =retfuente4[[#This Row],[Base mínima en UVT]]*$F$2 -> 0 | D46: 0.2
A47: Pagos o abonos en cuenta por concepto de rendimientos financieros, realizados a personas no residentes o no domiciliadas en el país, originados en créditos obtenidos en el exterior por término igual o superior a un (1) año o por concepto de intereses o costos financieros del canon de arrendamiento originados en contratos de leasing que se celebre directamente o a través de compañías de leasing con empresas extranjeras sin domicilio en Colombia, | B47: 0 | C47: =retfuente4[[#This Row],[Base mínima en UVT]]*$F$2 -> 0 | D47: 0.15
A48: Pagos o abonos en cuenta, originados en contratos de leasing sobre naves, helicópteros y/o aerodinos, así como sus partes que se celebren directamente o a través de compañías de leasing, con empresas extranjeras sin domicilio en Colombia. | B48: 0 | C48: =retfuente4[[#This Row],[Base mínima en UVT]]*$F$2 -> 0 | D48: 0.01
A49: Pagos o abonos en cuenta por concepto de rendimientos financieros o intereses, realizados a personas no residentes o no domiciliadas en el país, originados en créditos o valores de contenido crediticio, por término igual o superior a ocho (8) años, destinados a la financiación de proyectos de infraestructura bajo el esquema de Asociaciones Público-Privadas en el marco de la Ley 1508 de 2012. | B49: 0 | C49: =retfuente4[[#This Row],[Base mínima en UVT]]*$F$2 -> 0 | D49: 0.05
A50: Pagos o abonos en cuenta por concepto de prima cedida por reaseguros realizados a personas no residentes o no domiciliadas en el país. | B50: 0 | C50: =retfuente4[[#This Row],[Base mínima en UVT]]*$F$2 -> 0 | D50: 0.01
A51: Pagos o abono en cuenta por concepto de administración o dirección de que trata el artículo 124 del estatuto tributario, realizados a personas no residentes o no domiciliadas en el país. | B51: 0 | C51: =retfuente4[[#This Row],[Base mínima en UVT]]*$F$2 -> 0 | D51: 0.33

Sheet ret. ICA 2025 JULIO
A1: conceptos de retención | B1: Base mínima en UVT | C1: Base mínima en pesos | D1: Tarifa de retención.
A2: compras | B2: 10 | C2: 498000 | D2: 0.006
A3: servicios | B3: 10 | C3: 498000 | D3: 0.01

Sheet ret. fuente 2025 enero junio
A1: conceptos de retención | B1: Base mínima en UVT | C1: Base mínima en pesos | D1: Tarifa de retención. | F1: VALOR UVT
A2: Compras generales (declarantes) | B2: 27 | C2: =retfuente[[#This Row],[Base mínima en UVT]]*$F$2 -> 1344573 | D2: 0.025 | F2: 49799
A3: Compras generales (no declarantes) | B3: 27 | C3: =retfuente[[#This Row],[Base mínima en UVT]]*$F$2 -> 1344573 | D3: 0.035
A4: Compras con tarjeta débito o crédito | B4: 0 | C4: =retfuente[[#This Row],[Base mínima en UVT]]*$F$2 -> 0 | D4: 0.015
A5: Compras de bienes o productos agrícolas o pecuarios sin procesamiento industrial | B5: 92 | C5: =retfuente[[#This Row],[Base mínima en UVT]]*$F$2 -> 4581508 | D5: 0.015
A6: Compras de bienes o productos agrícolas o pecuarios con procesamiento industrial (declarantes) | B6: 27 | C6: =retfuente[[#This Row],[Base mínima en UVT]]*$F$2 -> 1344573 | D6: 0.025
A7: Compras de bienes o productos agrícolas o pecuarios con procesamiento industrial declarantes (no declarantes) | B7: 27 | C7: =retfuente[[#This Row],[Base mínima en UVT]]*$F$2 -> 1344573 | D7: 0.035
A8: Compras de café pergamino o cereza | B8: 160 | C8: =retfuente[[#This Row],[Base mínima en UVT]]*$F$2 -> 7967840 | D8: 0.005
A9: Compras de combustibles derivados del petróleo | B9: 0 | C9: =retfuente[[#This Row],[Base mínima en UVT]]*$F$2 -> 0 | D9: 0.001
A10: Enajenación de activos fijos de personas naturales (notarías y tránsito son agentes retenedores) | B10: 0 | C10: =retfuente[[#This Row],[Base mínima en UVT]]*$F$2 -> 0 | D10: 0.01
A11: Compras de vehículos | B11: 0 | C11: =retfuente[[#This Row],[Base mínima en UVT]]*$F$2 -> 0 | D11: 0.01
A12: Compras de bienes raíces cuya destinación y uso sea vivienda de habitación (por las primeras 20.000 UVT, es decir hasta $941.300.000) | B12: 0 | C12: =retfuente[[#This Row],[Base mínima en UVT]]*$F$2 -> 0 | D12: 0.01
A13: Compras de bienes raíces cuya destinación y uso sea vivienda de habitación (exceso de las primeras 20.000 UVT, es decir superior a $941.300.000) | B13: 20000 | C13: =retfuente[[#This Row],[Base mínima en UVT]]*$F$2 -> 995980000 | D13: 0.025
A14: Compras de bienes raíces cuya destinación y uso sea distinto a vivienda de habitación | B14: 0 | C14: =retfuente[[#This Row],[Base mínima en UVT]]*$F$2 -> 0 | D14: 0.025
... A43: Retención en la fuente por Iva en compras | B43: 27 | C43: =retfuente[[#This Row],[Base mínima en UVT]]*$F$2 -> 1344573 | D43: 0.15
A44: RETENCIÓN POR PAGOS AL EXTERIOR
A45: Pagos o abonos en cuenta por concepto de intereses, comisiones, honorarios, regalías, arrendamientos, compensaciones por servicios personales, o explotación de toda especie de propiedad industrial o del know-how, prestación de servicios, beneficios o regalías provenientes de la propiedad literaria, artística y científica, explotación de películas cinematográficas y explotación de software. | B45: 0 | C45: =retfuente[[#This Row],[Base mínima en UVT]]*$F$2 -> 0 | D45: 0.2
A46: Pagos o abonos en cuenta por concepto de consultorías, servicios técnicos y de asistencia técnica, prestados por personas no residentes o no domiciliadas en Colombia, | B46: 0 | C46: =retfuente[[#This Row],[Base mínima en UVT]]*$F$2 -> 0 | D46: 0.2
A47: Pagos o abonos en cuenta por concepto de rendimientos financieros, realizados a personas no residentes o no domiciliadas en el país, originados en créditos obtenidos en el exterior por término igual o superior a un (1) año o por concepto de intereses o costos financieros del canon de arrendamiento originados en contratos de leasing que se celebre directamente o a través de compañías de leasing con empresas extranjeras sin domicilio en Colombia, | B47: 0 | C47: =retfuente[[#This Row],[Base mínima en UVT]]*$F$2 -> 0 | D47: 0.15
A48: Pagos o abonos en cuenta, originados en contratos de leasing sobre naves, helicópteros y/o aerodinos, así como sus partes que se celebren directamente o a través de compañías de leasing, con empresas extranjeras sin domicilio en Colombia. | B48: 0 | C48: =retfuente[[#This Row],[Base mínima en UVT]]*$F$2 -> 0 | D48: 0.01
A49: Pagos o abonos en cuenta por concepto de rendimientos financieros o intereses, realizados a personas no residentes o no domiciliadas en el país, originados en créditos o valores de contenido crediticio, por término igual o superior a ocho (8) años, destinados a la financiación de proyectos de infraestructura bajo el esquema de Asociaciones Público-Privadas en el marco de la Ley 1508 de 2012. | B49: 0 | C49: =retfuente[[#This Row],[Base mínima en UVT]]*$F$2 -> 0 | D49: 0.05
A50: Pagos o abonos en cuenta por concepto de prima cedida por reaseguros realizados a personas no residentes o no domiciliadas en el país. | B50: 0 | C50: =retfuente[[#This Row],[Base mínima en UVT]]*$F$2 -> 0 | D50: 0.01
A51: Pagos o abono en cuenta por concepto de administración o dirección de que trata el artículo 124 del estatuto tributario, realizados a personas no residentes o no domiciliadas en el país. | B51: 0 | C51: =retfuente[[#This Row],[Base mínima en UVT]]*$F$2 -> 0 | D51: 0.33

Sheet ret. ICA 2025 enero junio
A1: conceptos de retención | B1: Base mínima en UVT | C1: Base mínima en pesos | D1: Tarifa de retención.
A2: compras | B2: 10 | C2: 471000 | D2: 0.006
A3: servicios | B3: 10 | C3: 471000 | D3: 0.01

Sheet RETENCION 2025
M1: TOTAL MES | R1: TOTAL MES | S1: TOTAL
F2: AÑO | G2: 2025 | I2: valor minimo de Ret. Fuente | M2: =Tabla36[[#Totals],[VALOR DE RETENCION]] -> 5355514.7 | N2: valor minimo de Ret. ICA | P2: 471000 | R2: =Tabla36[[#Totals],[VALOR DE RETE ICA]] -> 1349193.9 | S2: =R2+M2 -> 6704708.6
I3: valor minimo de Ret. Fuente junio 2025 | K3: 498000 | N3: valor minimo de Ret. Fuente junio 2025 | P3: 498000
I4: RETENCION EN LA FUENTE | N4: RETE ICA
B5: NOMBRE | C5: NIT | D5: Obra | E5: FECHA | F5: Nro factura | G5: Monto Factura | H5: Base Imponible | I5: Concepto | J5: VALOR MINIMO RETEFUENTE | K5: RETE FUENTE ? | L5: % de retencion | M5: VALOR DE RETENCION | N5: Concepto2 | O5: VALOR MINIMO RETE ICA | P5: RETE ICA? | Q5: % De Retencion2 | R5: VALOR DE RETE ICA | S5: Monto a cancelar en Caja | T5: Columna4 | U5: Impuesto por factura
B6: EL CONSTRUCTOR | C6: 1124848579 | D6: OLIMPICO | E6: 45750 | F6: 109314 | G6: 2334600 | H6: 1961849 | I6: Compras generales (declarantes) | J6: =VLOOKUP(I6,retfuente[],3,FALSE) -> 1344573 | K6: =IF(J6>=H6,"NO APLICA","APLICA") -> APLICA | L6: =VLOOKUP(I6,retfuente[],4,FALSE) -> 0.025 | M6: =IF(K6="APLICA",H6*L6,0) -> 49046.225 | N6: compras | O6: =VLOOKUP(N6,retICA[],3,FALSE) -> 471000 | P6: =IF($P$2>=H6,"NO APLICA","APLICA") -> APLICA | Q6: =VLOOKUP(N6,retICA[],4,FALSE) -> 0.006 | R6: =IF(P6="APLICA",H6*Q6,0) -> 11771.094 | S6: =G6-(R6+M6) -> 2273782.7 | U6: =G6-S6 -> 60817.319
B7: LB GROUP SAS | C7: 900698138-8 | D7: OLIMPICO | E7: 45768 | F7: LB2345 | G7: 5002800 | H7: 4204033.6 | I7: Compras generales (declarantes) | J7: =VLOOKUP(I7,retfuente[],3,FALSE) -> 1344573 | K7: =IF(J7>=H7,"NO APLICA","APLICA") -> APLICA | L7: =VLOOKUP(I7,retfuente[],4,FALSE) -> 0.025 | M7: =IF(K7="APLICA",H7*L7,0) -> 105100.84 | N7: compras | O7: =VLOOKUP(N7,retICA[],3,FALSE) -> 471000 | P7: =IF($P$2>=H7,"NO APLICA","APLICA") -> APLICA | Q7: =VLOOKUP(N7,retICA[],4,FALSE) -> 0.006 | R7: =IF(P7="APLICA",H7*Q7,0) -> 25224.202 | S7: =G7-(R7+M7) -> 4872475 | U7: =G7-S7 -> 130325.04
B8: COINSER LTDA | C8: 846000005-6 | D8: OLIMPICO | E8: 45770 | F8: 12807 | G8: 910000 | H8: 767227 | I8: Compras generales (declarantes) | J8: =VLOOKUP(I8,retfuente[],3,FALSE) -> 1344573 | K8: =IF(J8>=H8,"NO APLICA","APLICA") -> NO APLICA | L8: =VLOOKUP(I8,retfuente[],4,FALSE) -> 0.025 | M8: =IF(K8="APLICA",H8*L8,0) -> 0 | N8: compras | O8: =VLOOKUP(N8,retICA[],3,FALSE) -> 471000 | P8: =IF($P$2>=H8,"NO APLICA","APLICA") -> APLICA | Q8: =VLOOKUP(N8,retICA[],4,FALSE) -> 0.006 | R8: =IF(P8="APLICA",H8*Q8,0) -> 4603.362 | S8: =G8-(R8+M8) -> 905396.64 | U8: =G8-S8 -> 4603.362
B9: EL CONSTRUCTOR | C9: 1124848579 | D9: OLIMPICO | E9: 45755 | F9: 110490 | G9: 364400 | H9: 306218 | I9: Compras generales (declarantes) | J9: =VLOOKUP(I9,retfuente[],3,FALSE) -> 1344573 | K9: =IF(J9>=H9,"NO APLICA","APLICA") -> NO APLICA | L9: =VLOOKUP(I9,retfuente[],4,FALSE) -> 0.025 | M9: =IF(K9="APLICA",H9*L9,0) -> 0 | N9: compras | O9: =VLOOKUP(N9,retICA[],3,FALSE) -> 471000 | P9: =IF($P$2>=H9,"NO APLICA","APLICA") -> NO APLICA | Q9: =VLOOKUP(N9,retICA[],4,FALSE) -> 0.006 | R9: =IF(P9="APLICA",H9*Q9,0) -> 0 | S9: =G9-(R9+M9) -> 364400 | U9: =G9-S9 -> 0
B10: ACEROS DUVAN | C10: 1126456991 | D10: HORMIGA | E10: 45806 | F10: 8188 | G10: 1045000 | H10: 878151 | I10: Compras generales (declarantes) | J10: =VLOOKUP(I10,retfuente[],3,FALSE) -> 1344573 | K10: =IF(J10>=H10,"NO APLICA","APLICA") -> NO APLICA | L10: =VLOOKUP(I10,retfuente[],4,FALSE) -> 0.025 | M10: =IF(K10="APLICA",H10*L10,0) -> 0 | N10: compras | O10: =VLOOKUP(N10,retICA[],3,FALSE) -> 471000 | P10: =IF($P$3>=H10,"NO APLICA","APLICA") -> APLICA | Q10: =VLOOKUP(N10,retICA[],4,FALSE) -> 0.006 | R10: =IF(P10="APLICA",H10*Q10,0) -> 5268.906 | S10: =G10-(R10+M10) -> 1039731.1 | U10: =G10-S10 -> 5268.906
B11: ACEROS DUVAN | C11: 1126456991 | D11: HORMIGA | E11: 45806 | F11: 8194 | G11: 11582254 | H11: 9941849 | I11: Compras generales (declarantes) | J11: =VLOOKUP(I11,retfuente[],3,FALSE) -> 1344573 | K11: =IF(J11>=H11,"NO APLICA","APLICA") -> APLICA | L11: =VLOOKUP(I11,retfuente[],4,FALSE) -> 0.025 | M11: =IF(K11="APLICA",H11*L11,0) -> 248546.23 | N11: compras | O11: =VLOOKUP(N11,retICA[],3,FALSE) -> 471000 | P11: =IF($P$3>=H11,"NO APLICA","APLICA") -> APLICA | Q11: =VLOOKUP(N11,retICA[],4,FALSE) -> 0.006 | R11: =IF(P11="APLICA",H11*Q11,0) -> 59651.094 | S11: =G11-(R11+M11) -> 11274057 | U11: =G11-S11 -> 308197.32
B12: ACEROS DUVAN | C12: 1126456991 | D12: HORMIGA | E12: 45805 | F12: 5937 | G12: 16000 | H12: 13445 | I12: Compras generales (declarantes) | J12: =VLOOKUP(I12,retfuente[],3,FALSE) -> 1344573 | K12: =IF(J12>=H12,"NO APLICA","APLICA") -> NO APLICA | L12: =VLOOKUP(I12,retfuente[],4,FALSE) -> 0.025 | M12: =IF(K12="APLICA",H12*L12,0) -> 0 | N12: compras | O12: =VLOOKUP(N12,retICA[],3,FALSE) -> 471000 | P12: =IF($P$3>=H12,"NO APLICA","APLICA") -> NO APLICA | Q12: =VLOOKUP(N12,retICA[],4,FALSE) -> 0.006 | R12: =IF(P12="APLICA",H12*Q12,0) -> 0 | S12: =G12-(R12+M12) -> 16000 | U12: =G12-S12 -> 0
B13: ACEROS DUVAN | C13: 1126456991 | D13: HORMIGA | E13: 45803 | F13: 5889 | G13: 32000 | H13: 26891 | I13: Compras generales (declarantes) | J13: =VLOOKUP(I13,retfuente[],3,FALSE) -> 1344573 | K13: =IF(J13>=H13,"NO APLICA","APLICA") -> NO APLICA | L13: =VLOOKUP(I13,retfuente[],4,FALSE) -> 0.025 | M13: =IF(K13="APLICA",H13*L13,0) -> 0 | N13: compras | O13: =VLOOKUP(N13,retICA[],3,FALSE) -> 471000 | P13: =IF($P$3>=H13,"NO APLICA","APLICA") -> NO APLICA | Q13: =VLOOKUP(N13,retICA[],4,FALSE) -> 0.006 | R13: =IF(P13="APLICA",H13*Q13,0) -> 0 | S13: =G13-(R13+M13) -> 32000 | U13: =G13-S13 -> 0
B14: ACEROS DUVAN | C14: 1126456991 | D14: HORMIGA | E14: 45800 | F14: 5844 | G14: 680000 | H14: 571429 | I14: Compras generales (declarantes) | J14: =VLOOKUP(I14,retfuente[],3,FALSE) -> 1344573 | K14: =IF(J14>=H14,"NO APLICA","APLICA") -> NO APLICA | L14: =VLOOKUP(I14,retfuente[],4,FALSE) -> 0.025 | M14: =IF(K14="APLICA",H14*L14,0) -> 0 | N14: compras | O14: =VLOOKUP(N14,retICA[],3,FALSE) -> 471000 | P14: =IF($P$3>=H14,"NO APLICA","APLICA") -> APLICA | Q14: =VLOOKUP(N14,retICA[],4,FALSE) -> 0.006 | R14: =IF(P14="APLICA",H14*Q14,0) -> 3428.574 | S14: =G14-(R14+M14) -> 676571.43 | U14: =G14-S14 -> 3428.574
B15: ACEROS DUVAN | C15: 1126456991 | D15: HORMIGA | E15: 45798 | F15: 7970 | G15: 60000 | H15: 50420 | I15: Compras generales (declarantes) | J15: =VLOOKUP(I15,retfuente[],3,FALSE) -> 1344573 | K15: =IF(J15>=H15,"NO APLICA","APLICA") -> NO APLICA | L15: =VLOOKUP(I15,retfuente[],4,FALSE) -> 0.025 | M15: =IF(K15="APLICA",H15*L15,0) -> 0 | N15: compras | O15: =VLOOKUP(N15,retICA[],3,FALSE) -> 471000 | P15: =IF($P$3>=H15,"NO APLICA","APLICA") -> NO APLICA | Q15: =VLOOKUP(N15,retICA[],4,FALSE) -> 0.006 | R15: =IF(P15="APLICA",H15*Q15,0) -> 0 | S15: =G15-(R15+M15) -> 60000 | U15: =G15-S15 -> 0
B16: ACEROS DUVAN | C16: 1126456991 | D16: HORMIGA | E16: 45798 | F16: 10884 | G16: 680000 | H16: 571429 | I16: Compras generales (declarantes) | J16: =VLOOKUP(I16,retfuente[],3,FALSE) -> 1344573 | K16: =IF(J16>=H16,"NO APLICA","APLICA") -> NO APLICA | L16: =VLOOKUP(I16,retfuente[],4,FALSE) -> 0.025 | M16: =IF(K16="APLICA",H16*L16,0) -> 0 | N16: compras | O16: =VLOOKUP(N16,retICA[],3,FALSE) -> 471000 | P16: =IF($P$3>=H16,"NO APLICA","APLICA") -> APLICA | Q16: =VLOOKUP(N16,retICA[],4,FALSE) -> 0.006 | R16: =IF(P16="APLICA",H16*Q16,0) -> 3428.574 | S16: =G16-(R16+M16) -> 676571.43 | U16: =G16-S16 -> 3428.574
B17: ACEROS DUVAN | C17: 1126456991 | D17: HORMIGA | E17: 45797 | F17: 7952 | G17: 52000 | H17: 43697 | I17: Compras generales (declarantes) | J17: =VLOOKUP(I17,retfuente[],3,FALSE) -> 1344573 | K17: =IF(J17>=H17,"NO APLICA","APLICA") -> NO APLICA | L17: =VLOOKUP(I17,retfuente[],4,FALSE) -> 0.025 | M17: =IF(K17="APLICA",H17*L17,0) -> 0 | N17: compras | O17: =VLOOKUP(N17,retICA[],3,FALSE) -> 471000 | P17: =IF($P$3>=H17,"NO APLICA","APLICA") -> NO APLICA | Q17: =VLOOKUP(N17,retICA[],4,FALSE) -> 0.006 | R17: =IF(P17="APLICA",H17*Q17,0) -> 0 | S17: =G17-(R17+M17) -> 52000 | U17: =G17-S17 -> 0
B18: ACEROS DUVAN | C18: 1126456991 | D18: HORMIGA | E18: 45792 | F18: 5704 | G18: 1096000 | H18: 921008 | I18: Compras generales (declarantes) | J18: =VLOOKUP(I18,retfuente[],3,FALSE) -> 1344573 | K18: =IF(J18>=H18,"NO APLICA","APLICA") -> NO APLICA | L18: =VLOOKUP(I18,retfuente[],4,FALSE) -> 0.025 | M18: =IF(K18="APLICA",H18*L18,0) -> 0 | N18: compras | O18: =VLOOKUP(N18,retICA[],3,FALSE) -> 471000 | P18: =IF($P$3>=H18,"NO APLICA","APLICA") -> APLICA | Q18: =VLOOKUP(N18,retICA[],4,FALSE) -> 0.006 | R18: =IF(P18="APLICA",H18*Q18,0) -> 5526.048 | S18: =G18-(R18+M18) -> 1090474 | U18: =G18-S18 -> 5526.048
B19: ACEROS DUVAN | C19: 1126456991 | D19: HORMIGA | E19: 45789 | F19: 7685 | G19: 31000 | H19: 26050 | I19: Compras generales (declarantes) | J19: =VLOOKUP(I19,retfuente[],3,FALSE) -> 1344573 | K19: =IF(J19>=H19,"NO APLICA","APLICA") -> NO APLICA | L19: =VLOOKUP(I19,retfuente[],4,FALSE) -> 0.025 | M19: =IF(K19="APLICA",H19*L19,0) -> 0 | N19: compras | O19: =VLOOKUP(N19,retICA[],3,FALSE) -> 471000 | P19: =IF($P$3>=H19,"NO APLICA","APLICA") -> NO APLICA | Q19: =VLOOKUP(N19,retICA[],4,FALSE) -> 0.006 | R19: =IF(P19="APLICA",H19*Q19,0) -> 0 | S19: =G19-(R19+M19) -> 31000 | U19: =G19-S19 -> 0
B20: ACEROS DUVAN | C20: 1126456991 | D20: HORMIGA | E20: 45787 | F20: 10637 | G20: 172000 | H20: 144538 | I20: Compras generales (declarantes) | J20: =VLOOKUP(I20,retfuente[],3,FALSE) -> 1344573 | K20: =IF(J20>=H20,"NO APLICA","APLICA") -> NO APLICA | L20: =VLOOKUP(I20,retfuente[],4,FALSE) -> 0.025 | M20: =IF(K20="APLICA",H20*L20,0) -> 0 | N20: compras | O20: =VLOOKUP(N20,retICA[],3,FALSE) -> 471000 | P20: =IF($P$3>=H20,"NO APLICA","APLICA") -> NO APLICA | Q20: =VLOOKUP(N20,retICA[],4,FALSE) -> 0.006 | R20: =IF(P20="APLICA",H20*Q20,0) -> 0 | S20: =G20-(R20+M20) -> 172000 | U20: =G20-S20 -> 0
B21: ACEROS DUVAN | C21: 1126456991 | D21: HORMIGA | E21: 45786 | F21: 5587 | G21: 25000 | H21: 21008 | I21: Compras generales (declarantes) | J21: =VLOOKUP(I21,retfuente[],3,FALSE) -> 1344573 | K21: =IF(J21>=H21,"NO APLICA","APLICA") -> NO APLICA | L21: =VLOOKUP(I21,retfuente[],4,FALSE) -> 0.025 | M21: =IF(K21="APLICA",H21*L21,0) -> 0 | N21: compras | O21: =VLOOKUP(N21,retICA[],3,FALSE) -> 471000 | P21: =IF($P$3>=H21,"NO APLICA","APLICA") -> NO APLICA | Q21: =VLOOKUP(N21,retICA[],4,FALSE) -> 0.006 | R21: =IF(P21="APLICA",H21*Q21,0) -> 0 | S21: =G21-(R21+M21) -> 25000 | U21: =G21-S21 -> 0
B22: SISCONT LIMITADA | C22: 814000143-8 | D22: HORMIGA | E22: 45783 | F22: 11E9215 | G22: 4567475 | H22: 3838214.3 | I22: Compras generales (declarantes) | J22: =VLOOKUP(I22,retfuente[],3,FALSE) -> 1344573 | K22: =IF(J22>=H22,"NO APLICA","APLICA") -> APLICA | L22: =VLOOKUP(I22,retfuente[],4,FALSE) -> 0.025 | M22: =IF(K22="APLICA",H22*L22,0) -> 95955.357 | N22: compras | O22: =VLOOKUP(N22,retICA[],3,FALSE) -> 471000 | P22: =IF($P$3>=H22,"NO APLICA","APLICA") -> APLICA | Q22: =VLOOKUP(N22,retICA[],4,FALSE) -> 0.006 | R22: =IF(P22="APLICA",H22*Q22,0) -> 23029.286 | S22: =G22-(R22+M22) -> 4448490.4 | U22: =G22-S22 -> 118984.64
B23: SISCONT LIMITADA | C23: 814000143-8 | D23: PRADO NORTE | E23: 45812 | F23: 01E43620 | G23: 8987423 | H23: 7552456.3 | I23: Compras generales (declarantes) | J23: =VLOOKUP(I23,retfuente[],3,FALSE) -> 1344573 | K23: =IF(J23>=H23,"NO APLICA","APLICA") -> APLICA | L23: =VLOOKUP(I23,retfuente[],4,FALSE) -> 0.025 | M23: =IF(K23="APLICA",H23*L23,0) -> 188811.41 | N23: compras | O23: =VLOOKUP(N23,retICA[],3,FALSE) -> 471000 | P23: =IF($P$3>=H23,"NO APLICA","APLICA") -> APLICA | Q23: =VLOOKUP(N23,retICA[],4,FALSE) -> 0.006 | R23: =IF(P23="APLICA",H23*Q23,0) -> 45314.738 | S23: =G23-(R23+M23) -> 8753296.9 | U23: =G23-S23 -> 234126.15
B24: ACEROS DUVAN | C24: 1126456991 | D24: HORMIGA | E24: 45819 | F24: 8528 | G24: 700000 | H24: 588235 | I24: Compras generales (declarantes) | J24: =VLOOKUP(I24,retfuente[],3,FALSE) -> 1344573 | K24: =IF(J24>=H24,"NO APLICA","APLICA") -> NO APLICA | L24: =VLOOKUP(I24,retfuente[],4,FALSE) -> 0.025 | M24: =IF(K24="APLICA",H24*L24,0) -> 0 | N24: compras | O24: =VLOOKUP(N24,retICA[],3,FALSE) -> 471000 | P24: =IF($P$3>=H24,"NO APLICA","APLICA") -> APLICA | Q24: =VLOOKUP(N24,retICA[],4,FALSE) -> 0.006 | R24: =IF(P24="APLICA",H24*Q24,0) -> 3529.41 | S24: =G24-(R24+M24) -> 696470.59 | U24: =G24-S24 -> 3529.41
B25: ACEROS DUVAN | C25: 1126456991 | D25: HORMIGA | E25: 45820 | F25: 8554 | G25: 1074000 | H25: 902521 | I25: Compras generales (declarantes) | J25: =VLOOKUP(I25,retfuente[],3,FALSE) -> 1344573 | K25: =IF(J25>=H25,"NO APLICA","APLICA") -> NO APLICA | L25: =VLOOKUP(I25,retfuente[],4,FALSE) -> 0.025 | M25: =IF(K25="APLICA",H25*L25,0) -> 0 | N25: compras | O25: =VLOOKUP(N25,retICA[],3,FALSE) -> 471000 | P25: =IF($P$3>=H25,"NO APLICA","APLICA") -> APLICA | Q25: =VLOOKUP(N25,retICA[],4,FALSE) -> 0.006 | R25: =IF(P25="APLICA",H25*Q25,0) -> 5415.126 | S25: =G25-(R25+M25) -> 1068584.9 | U25: =G25-S25 -> 5415.126
B26: SISCONT LIMITADA | C26: 814000143-8 | D26: PRADO NORTE | E26: 45814 | F26: 11E9536 | G26: 784218 | H26: 659006.72 | I26: Compras generales (declarantes) | J26: =VLOOKUP(I26,retfuente[],3,FALSE) -> 1344573 | K26: =IF(J26>=H26,"NO APLICA","APLICA") -> NO APLICA | L26: =VLOOKUP(I26,retfuente[],4,FALSE) -> 0.025 | M26: =IF(K26="APLICA",H26*L26,0) -> 0 | N26: compras | O26: =VLOOKUP(N26,retICA[],3,FALSE) -> 471000 | P26: =IF($P$3>=H26,"NO APLICA","APLICA") -> APLICA | Q26: =VLOOKUP(N26,retICA[],4,FALSE) -> 0.006 | R26: =IF(P26="APLICA",H26*Q26,0) -> 3954.0403 | S26: =G26-(R26+M26) -> 780263.96 | U26: =G26-S26 -> 3954.0403
B27: ACEROS DUVAN | C27: 1126456991 | D27: HORMIGA | E27: 45810 | F27: 8274 | G27: 2725513 | H27: 2339496 | I27: Compras generales (declarantes) | J27: =VLOOKUP(I27,retfuente[],3,FALSE) -> 1344573 | K27: =IF(J27>=H27,"NO APLICA","APLICA") -> APLICA | L27: =VLOOKUP(I27,retfuente[],4,FALSE) -> 0.025 | M27: =IF(K27="APLICA",H27*L27,0) -> 58487.4 | N27: compras | O27: =VLOOKUP(N27,retICA[],3,FALSE) -> 471000 | P27: =IF($P$3>=H27,"NO APLICA","APLICA") -> APLICA | Q27: =VLOOKUP(N27,retICA[],4,FALSE) -> 0.006 | R27: =IF(P27="APLICA",H27*Q27,0) -> 14036.976 | S27: =G27-(R27+M27) -> 2652988.6 | U27: =G27-S27 -> 72524.376
B28: EL CONSTRUCTOR | C28: 1124848579 | E28: 45826 | F28: 122154 | G28: 21363938 | H28: 17952889 | I28: Compras generales (declarantes) | J28: =VLOOKUP(I28,retfuente[],3,FALSE) -> 1344573 | K28: =IF(J28>=H28,"NO APLICA","APLICA") -> APLICA | L28: =VLOOKUP(I28,retfuente[],4,FALSE) -> 0.025 | M28: =IF(K28="APLICA",H28*L28,0) -> 448822.23 | N28: compras | O28: =VLOOKUP(N28,retICA[],3,FALSE) -> 471000 | P28: =IF($P$2>=H28,"NO APLICA","APLICA") -> APLICA | Q28: =VLOOKUP(N28,retICA[],4,FALSE) -> 0.006 | R28: =IF(P28="APLICA",H28*Q28,0) -> 107717.33 | S28: =G28-(R28+M28) -> 20807398 | U28: =G28-S28 -> 556539.56
B29: ACEROS DUVAN | C29: 1126456991 | D29: HORMIGA | E29: 45812 | F29: 6112 | G29: 20500 | H29: 17227 | I29: Compras generales (declarantes) | J29: =VLOOKUP(I29,retfuente[],3,FALSE) -> 1344573 | K29: =IF(J29>=H29,"NO APLICA","APLICA") -> NO APLICA | L29: =VLOOKUP(I29,retfuente[],4,FALSE) -> 0.025 | M29: =IF(K29="APLICA",H29*L29,0) -> 0 | N29: compras | O29: =VLOOKUP(N29,retICA[],3,FALSE) -> 471000 | P29: =IF($P$3>=H29,"NO APLICA","APLICA") -> NO APLICA | Q29: =VLOOKUP(N29,retICA[],4,FALSE) -> 0.006 | R29: =IF(P29="APLICA",H29*Q29,0) -> 0 | S29: =G29-(R29+M29) -> 20500 | U29: =G29-S29 -> 0
B30: ACEROS DUVAN | C30: 1126456991 | D30: HORMIGA | E30: 45813 | F30: 8383 | G30: 1022000 | H30: 858824 | I30: Compras generales (declarantes) | J30: =VLOOKUP(I30,retfuente[],3,FALSE) -> 1344573 | K30: =IF(J30>=H30,"NO APLICA","APLICA") -> NO APLICA | L30: =VLOOKUP(I30,retfuente[],4,FALSE) -> 0.025 | M30: =IF(K30="APLICA",H30*L30,0) -> 0 | N30: compras | O30: =VLOOKUP(N30,retICA[],3,FALSE) -> 471000 | P30: =IF($P$3>=H30,"NO APLICA","APLICA") -> APLICA | Q30: =VLOOKUP(N30,retICA[],4,FALSE) -> 0.006 | R30: =IF(P30="APLICA",H30*Q30,0) -> 5152.944 | S30: =G30-(R30+M30) -> 1016847.1 | U30: =G30-S30 -> 5152.944
B31: ACEROS DUVAN | C31: 1126456991 | D31: HORMIGA | E31: 45821 | F31: 11401 | G31: 26100 | H31: 21933 | I31: Compras generales (declarantes) | J31: =VLOOKUP(I31,retfuente[],3,FALSE) -> 1344573 | K31: =IF(J31>=H31,"NO APLICA","APLICA") -> NO APLICA | L31: =VLOOKUP(I31,retfuente[],4,FALSE) -> 0.025 | M31: =IF(K31="APLICA",H31*L31,0) -> 0 | N31: compras | O31: =VLOOKUP(N31,retICA[],3,FALSE) -> 471000 | P31: =IF($P$3>=H31,"NO APLICA","APLICA") -> NO APLICA | Q31: =VLOOKUP(N31,retICA[],4,FALSE) -> 0.006 | R31: =IF(P31="APLICA",H31*Q31,0) -> 0 | S31: =G31-(R31+M31) -> 26100 | U31: =G31-S31 -> 0
B32: ACEROS DUVAN | C32: 1126456991 | D32: HORMIGA | E32: 45825 | F32: 11448 | G32: 1069000 | H32: 898319 | I32: Compras generales (declarantes) | J32: =VLOOKUP(I32,retfuente[],3,FALSE) -> 1344573 | K32: =IF(J32>=H32,"NO APLICA","APLICA") -> NO APLICA | L32: =VLOOKUP(I32,retfuente[],4,FALSE) -> 0.025 | M32: =IF(K32="APLICA",H32*L32,0) -> 0 | N32: compras | O32: =VLOOKUP(N32,retICA[],3,FALSE) -> 471000 | P32: =IF($P$3>=H32,"NO APLICA","APLICA") -> APLICA | Q32: =VLOOKUP(N32,retICA[],4,FALSE) -> 0.006 | R32: =IF(P32="APLICA",H32*Q32,0) -> 5389.914 | S32: =G32-(R32+M32) -> 1063610.1 | U32: =G32-S32 -> 5389.914
B33: ACEROS DUVAN | C33: 1126456991 | D33: HORMIGA | E33: 45827 | F33: 8772 | G33: 1036000 | H33: 870588 | I33: Compras generales (declarantes) | J33: =VLOOKUP(I33,retfuente[],3,FALSE) -> 1344573 | K33: =IF(J33>=H33,"NO APLICA","APLICA") -> NO APLICA | L33: =VLOOKUP(I33,retfuente[],4,FALSE) -> 0.025 | M33: =IF(K33="APLICA",H33*L33,0) -> 0 | N33: compras | O33: =VLOOKUP(N33,retICA[],3,FALSE) -> 471000 | P33: =IF($P$3>=H33,"NO APLICA","APLICA") -> APLICA | Q33: =VLOOKUP(N33,retICA[],4,FALSE) -> 0.006 | R33: =IF(P33="APLICA",H33*Q33,0) -> 5223.528 | S33: =G33-(R33+M33) -> 1030776.5 | U33: =G33-S33 -> 5223.528
B34: ACEROS DUVAN | C34: 1126456991 | D34: HORMIGA | E34: 45828 | F34: 6526 | G34: 28000 | H34: 23529 | I34: Compras generales (declarantes) | J34: =VLOOKUP(I34,retfuente[],3,FALSE) -> 1344573 | K34: =IF(J34>=H34,"NO APLICA","APLICA") -> NO APLICA | L34: =VLOOKUP(I34,retfuente[],4,FALSE) -> 0.025 | M34: =IF(K34="APLICA",H34*L34,0) -> 0 | N34: compras | O34: =VLOOKUP(N34,retICA[],3,FALSE) -> 471000 | P34: =IF($P$3>=H34,"NO APLICA","APLICA") -> NO APLICA | Q34: =VLOOKUP(N34,retICA[],4,FALSE) -> 0.006 | R34: =IF(P34="APLICA",H34*Q34,0) -> 0 | S34: =G34-(R34+M34) -> 28000 | U34: =G34-S34 -> 0
B35: ACEROS DUVAN | C35: 1126456991 | D35: HORMIGA | E35: 45831 | F35: 11641 | G35: 1020109 | H35: 875630 | I35: Compras generales (declarantes) | J35: =VLOOKUP(I35,retfuente[],3,FALSE) -> 1344573 | K35: =IF(J35>=H35,"NO APLICA","APLICA") -> NO APLICA | L35: =VLOOKUP(I35,retfuente[],4,FALSE) -> 0.025 | M35: =IF(K35="APLICA",H35*L35,0) -> 0 | N35: compras | O35: =VLOOKUP(N35,retICA[],3,FALSE) -> 471000 | P35: =IF($P$3>=H35,"NO APLICA","APLICA") -> APLICA | Q35: =VLOOKUP(N35,retICA[],4,FALSE) -> 0.006 | R35: =IF(P35="APLICA",H35*Q35,0) -> 5253.78 | S35: =G35-(R35+M35) -> 1014855.2 | U35: =G35-S35 -> 5253.78
B36: ACEROS DUVAN | C36: 1126456991 | D36: HORMIGA | E36: 45836 | F36: 634 | G36: 745502 | H36: 639916 | I36: Compras generales (declarantes) | J36: =VLOOKUP(I36,retfuente[],3,FALSE) -> 1344573 | K36: =IF(J36>=H36,"NO APLICA","APLICA") -> NO APLICA | L36: =VLOOKUP(I36,retfuente[],4,FALSE) -> 0.025 | M36: =IF(K36="APLICA",H36*L36,0) -> 0 | N36: compras | O36: =VLOOKUP(N36,retICA[],3,FALSE) -> 471000 | P36: =IF($P$3>=H36,"NO APLICA","APLICA") -> APLICA | Q36: =VLOOKUP(N36,retICA[],4,FALSE) -> 0.006 | R36: =IF(P36="APLICA",H36*Q36,0) -> 3839.496 | S36: =G36-(R36+M36) -> 741662.5 | U36: =G36-S36 -> 3839.496
B37: ACEROS DUVAN | C37: 1126456991 | D37: HORMIGA | E37: 45836 | F37: 9017 | G37: 748831 | H37: 642773 | I37: Compras generales (declarantes) | J37: =VLOOKUP(I37,retfuente[],3,FALSE) -> 1344573 | K37: =IF(J37>=H37,"NO APLICA","APLICA") -> NO APLICA | L37: =VLOOKUP(I37,retfuente[],4,FALSE) -> 0.025 | M37: =IF(K37="APLICA",H37*L37,0) -> 0 | N37: compras | O37: =VLOOKUP(N37,retICA[],3,FALSE) -> 471000 | P37: =IF($P$3>=H37,"NO APLICA","APLICA") -> APLICA | Q37: =VLOOKUP(N37,retICA[],4,FALSE) -> 0.006 | R37: =IF(P37="APLICA",H37*Q37,0) -> 3856.638 | S37: =G37-(R37+M37) -> 744974.36 | U37: =G37-S37 -> 3856.638
B38: ACEROS DUVAN | C38: 1126456991 | D38: HORMIGA | E38: 45838 | F38: 9061 | G38: 3446050 | H38: 2957983 | I38: Compras generales (declarantes) | J38: =VLOOKUP(I38,retfuente[],3,FALSE) -> 1344573 | K38: =IF(J38>=H38,"NO APLICA","APLICA") -> APLICA | L38: =VLOOKUP(I38,retfuente[],4,FALSE) -> 0.025 | M38: =IF(K38="APLICA",H38*L38,0) -> 73949.575 | N38: compras | O38: =VLOOKUP(N38,retICA[],3,FALSE) -> 471000 | P38: =IF($P$3>=H38,"NO APLICA","APLICA") -> APLICA | Q38: =VLOOKUP(N38,retICA[],4,FALSE) -> 0.006 | R38: =IF(P38="APLICA",H38*Q38,0) -> 17747.898 | S38: =G38-(R38+M38) -> 3354352.5 | U38: =G38-S38 -> 91697.473
B39: ACEROS DUVAN | C39: 1126456991 | D39: HORMIGA | E39: 45846 | F39: 6955 | G39: 2778378 | H39: 2384874 | I39: Compras generales (declarantes) | J39: =VLOOKUP(I39,retfuente4[#All],3,FALSE) -> 498000 | K39: =IF(J39>=H39,"NO APLICA","APLICA") -> APLICA | L39: =VLOOKUP(I39,retfuente4[#All],4,FALSE) -> 0.025 | M39: =IF(K39="APLICA",H39*L39,0) -> 59621.85 | N39: compras | O39: =VLOOKUP(N39,RETEICAJULIO2025,3,FALSE) -> 498000 | P39: =IF($P$3>=H39,"NO APLICA","APLICA") -> APLICA | Q39: =VLOOKUP(N39,RETEICAJULIO2025,4,FALSE) -> 0.006 | R39: =IF(P39="APLICA",H39*Q39,0) -> 14309.244 | S39: =G39-(R39+M39) -> 2704446.9 | U39: =G39-S39 -> 73931.094
B40: ACEROS DUVAN | C40: 1126456991 | D40: HORMIGA | E40: 45848 | F40: 9337 | G40: 44000 | H40: 36975 | I40: Compras generales (declarantes) | J40: =VLOOKUP(I40,retfuente4[#All],3,FALSE) -> 498000 | K40: =IF(J40>=H40,"NO APLICA","APLICA") -> NO APLICA | L40: =VLOOKUP(I40,retfuente4[#All],4,FALSE) -> 0.025 | M40: =IF(K40="APLICA",H40*L40,0) -> 0 | N40: compras | O40: =VLOOKUP(N40,RETEICAJULIO2025,3,FALSE) -> 498000 | P40: =IF($P$3>=H40,"NO APLICA","APLICA") -> NO APLICA | Q40: =VLOOKUP(N40,RETEICAJULIO2025,4,FALSE) -> 0.006 | R40: =IF(P40="APLICA",H40*Q40,0) -> 0 | S40: =G40-(R40+M40) -> 44000 | U40: =G40-S40 -> 0
B41: ACEROS DUVAN | C41: 1126456991 | D41: HORMIGA | E41: 45849 | F41: 7054 | G41: 1305975 | H41: 1121008 | I41: Compras generales (declarantes) | J41: =VLOOKUP(I41,retfuente4[#All],3,FALSE) -> 498000 | K41: =IF(J41>=H41,"NO APLICA","APLICA") -> APLICA | L41: =VLOOKUP(I41,retfuente4[#All],4,FALSE) -> 0.025 | M41: =IF(K41="APLICA",H41*L41,0) -> 28025.2 | N41: compras | O41: =VLOOKUP(N41,RETEICAJULIO2025,3,FALSE) -> 498000 | P41: =IF($P$3>=H41,"NO APLICA","APLICA") -> APLICA | Q41: =VLOOKUP(N41,RETEICAJULIO2025,4,FALSE) -> 0.006 | R41: =IF(P41="APLICA",H41*Q41,0) -> 6726.048 | S41: =G41-(R41+M41) -> 1271223.8 | U41: =G41-S41 -> 34751.248
B42: SISCONT LIMITADA | C42: 814000143-8 | D42: PRADO NORTE | E42: 45852 | F42: 11E9952 | G42: 2098231 | H42: 1763219.3 | I42: Compras generales (declarantes) | J42: =VLOOKUP(I42,retfuente4[#All],3,FALSE) -> 498000 | K42: =IF(J42>=H42,"NO APLICA","APLICA") -> APLICA | L42: =VLOOKUP(I42,retfuente4[#All],4,FALSE) -> 0.025 | M42: =IF(K42="APLICA",H42*L42,0) -> 44080.483 | N42: compras | O42: =VLOOKUP(N42,RETEICAJULIO2025,3,FALSE) -> 498000 | P42: =IF($P$3>=H42,"NO APLICA","APLICA") -> APLICA | Q42: =VLOOKUP(N42,RETEICAJULIO2025,4,FALSE) -> 0.006 | R42: =IF(P42="APLICA",H42*Q42,0) -> 10579.316 | S42: =G42-(R42+M42) -> 2043571.2 | U42: =G42-S42 -> 54659.799
B43: SISCONT LIMITADA | C43: 814000143-8 | D43: OLIMPICO | E43: 45852 | F43: 11E9954 | G43: 230059 | H43: 193326.89 | I43: Compras generales (declarantes) | J43: =VLOOKUP(I43,retfuente4[#All],3,FALSE) -> 498000 | K43: =IF(J43>=H43,"NO APLICA","APLICA") -> NO APLICA | L43: =VLOOKUP(I43,retfuente4[#All],4,FALSE) -> 0.025 | M43: =IF(K43="APLICA",H43*L43,0) -> 0 | N43: compras | O43: =VLOOKUP(N43,RETEICAJULIO2025,3,FALSE) -> 498000 | P43: =IF($P$3>=H43,"NO APLICA","APLICA") -> NO APLICA | Q43: =VLOOKUP(N43,RETEICAJULIO2025,4,FALSE) -> 0.006 | R43: =IF(P43="APLICA",H43*Q43,0) -> 0 | S43: =G43-(R43+M43) -> 230059 | U43: =G43-S43 -> 0
B44: EL CONSTRUCTOR | C44: 1124848579 | E44: 45852 | F44: 125699 | G44: 569940 | H44: 478941 | I44: Compras generales (declarantes) | J44: =VLOOKUP(I44,retfuente4[#All],3,FALSE) -> 498000 | K44: =IF(J44>=H44,"NO APLICA","APLICA") -> NO APLICA | L44: =VLOOKUP(I44,retfuente4[#All],4,FALSE) -> 0.025 | M44: =IF(K44="APLICA",H44*L44,0) -> 0 | N44: compras | O44: =VLOOKUP(N44,RETEICAJULIO2025,3,FALSE) -> 498000 | P44: =IF($P$3>=H44,"NO APLICA","APLICA") -> NO APLICA | Q44: =VLOOKUP(N44,RETEICAJULIO2025,4,FALSE) -> 0.006 | R44: =IF(P44="APLICA",H44*Q44,0) -> 0 | S44: =G44-(R44+M44) -> 569940 | U44: =G44-S44 -> 0
B45: EL CONSTRUCTOR | C45: 1124848579 | D45: VILLAGARZON | E45: 45856 | F45: 126551 | G45: 1725000 | H45: 1449580 | I45: Compras generales (declarantes) | J45: =VLOOKUP(I45,retfuente4[#All],3,FALSE) -> 498000 | K45: =IF(J45>=H45,"NO APLICA","APLICA") -> APLICA | L45: =VLOOKUP(I45,retfuente4[#All],4,FALSE) -> 0.025 | M45: =IF(K45="APLICA",H45*L45,0) -> 36239.5 | N45: compras | O45: =VLOOKUP(N45,RETEICAJULIO2025,3,FALSE) -> 498000 | P45: =IF($P$3>=H45,"NO APLICA","APLICA") -> APLICA | Q45: =VLOOKUP(N45,RETEICAJULIO2025,4,FALSE) -> 0.006 | R45: =IF(P45="APLICA",H45*Q45,0) -> 8697.48 | S45: =G45-(R45+M45) -> 1680063 | U45: =G45-S45 -> 44936.98
B46: EL CONSTRUCTOR | C46: 1124848579 | D46: VILLAGARZON | E46: 45856 | F46: 126558 | G46: 697569 | H46: 586192 | I46: Compras generales (declarantes) | J46: =VLOOKUP(I46,retfuente4[#All],3,FALSE) -> 498000 | K46: =IF(J46>=H46,"NO APLICA","APLICA") -> APLICA | L46: =VLOOKUP(I46,retfuente4[#All],4,FALSE) -> 0.025 | M46: =IF(K46="APLICA",H46*L46,0) -> 14654.8 | N46: compras | O46: =VLOOKUP(N46,RETEICAJULIO2025,3,FALSE) -> 498000 | P46: =IF($P$3>=H46,"NO APLICA","APLICA") -> APLICA | Q46: =VLOOKUP(N46,RETEICAJULIO2025,4,FALSE) -> 0.006 | R46: =IF(P46="APLICA",H46*Q46,0) -> 3517.152 | S46: =G46-(R46+M46) -> 679397.05 | U46: =G46-S46 -> 18171.952
B47: ACEROS DUVAN | C47: 1126456991 | D47: HORMIGA | E47: 45856 | F47: 9529 | G47: 157500 | H47: 132353 | I47: Compras generales (declarantes) | J47: =VLOOKUP(I47,retfuente4[#All],3,FALSE) -> 498000 | K47: =IF(J47>=H47,"NO APLICA","APLICA") -> NO APLICA | L47: =VLOOKUP(I47,retfuente4[#All],4,FALSE) -> 0.025 | M47: =IF(K47="APLICA",H47*L47,0) -> 0 | N47: compras | O47: =VLOOKUP(N47,RETEICAJULIO2025,3,FALSE) -> 498000 | P47: =IF($P$3>=H47,"NO APLICA","APLICA") -> NO APLICA | Q47: =VLOOKUP(N47,RETEICAJULIO2025,4,FALSE) -> 0.006 | R47: =IF(P47="APLICA",H47*Q47,0) -> 0 | S47: =G47-(R47+M47) -> 157500 | U47: =G47-S47 -> 0
B48: SISCONT LIMITADA | C48: 814000143-8 | D48: PRADO NORTE | E48: 45856 | F48: 11E10005 | G48: 161818 | H48: 98166.39 | I48: Compras generales (declarantes) | J48: =VLOOKUP(I48,retfuente4[#All],3,FALSE) -> 498000 | K48: =IF(J48>=H48,"NO APLICA","APLICA") -> NO APLICA | L48: =VLOOKUP(I48,retfuente4[#All],4,FALSE) -> 0.025 | M48: =IF(K48="APLICA",H48*L48,0) -> 0 | N48: compras | O48: =VLOOKUP(N48,RETEICAJULIO2025,3,FALSE) -> 498000 | P48: =IF($P$3>=H48,"NO APLICA","APLICA") -> NO APLICA | Q48: =VLOOKUP(N48,RETEICAJULIO2025,4,FALSE) -> 0.006 | R48: =IF(P48="APLICA",H48*Q48,0) -> 0 | S48: =G48-(R48+M48) -> 161818 | U48: =G48-S48 -> 0
B49: COLMEGA S.A.S | C49: 901517169 | E49: 45859 | F49: FVE 1 | G49: 5821199.2 | H49: 5022605 | I49: Compras generales (declarantes) | J49: =VLOOKUP(I49,retfuente4[#All],3,FALSE) -> 498000 | K49: =IF(J49>=H49,"NO APLICA","APLICA") -> APLICA | L49: =VLOOKUP(I49,retfuente4[#All],4,FALSE) -> 0.025 | M49: =IF(K49="APLICA",H49*L49,0) -> 125565.12 | N49: compras | O49: =VLOOKUP(N49,RETEICAJULIO2025,3,FALSE) -> 498000 | P49: =IF($P$3>=H49,"NO APLICA","APLICA") -> APLICA | Q49: =VLOOKUP(N49,RETEICAJULIO2025,4,FALSE) -> 0.006 | R49: =IF(P49="APLICA",H49*Q49,0) -> 30135.63 | S49: =G49-(R49+M49) -> 5665498.4 | U49: =G49-S49 -> 155700.75
B50: CERAMICAS BENAVIDES | C50: 1127071533-1 | E50: 45859 | F50: FECB1571 | G50: 1488135.6 | H50: 1277369.6 | I50: Compras generales (declarantes) | J50: =VLOOKUP(I50,retfuente4[#All],3,FALSE) -> 498000 | K50: =IF(J50>=H50,"NO APLICA","APLICA") -> APLICA | L50: =VLOOKUP(I50,retfuente4[#All],4,FALSE) -> 0.025 | M50: =IF(K50="APLICA",H50*L50,0) -> 31934.241 | N50: compras | O50: =VLOOKUP(N50,RETEICAJULIO2025,3,FALSE) -> 498000 | P50: =IF($P$3>=H50,"NO APLICA","APLICA") -> APLICA | Q50: =VLOOKUP(N50,RETEICAJULIO2025,4,FALSE) -> 0.006 | R50: =IF(P50="APLICA",H50*Q50,0) -> 7664.2178 | S50: =G50-(R50+M50) -> 1448537.2 | U50: =G50-S50 -> 39598.459
B51: ACEROS DUVAN | C51: 1126456991 | D51: HORMIGA | E51: 45860 | F51: 12344 | G51: 80000 | H51: 67227 | I51: Compras generales (declarantes) | J51: =VLOOKUP(I51,retfuente4[#All],3,FALSE) -> 498000 | K51: =IF(J51>=H51,"NO APLICA","APLICA") -> NO APLICA | L51: =VLOOKUP(I51,retfuente4[#All],4,FALSE) -> 0.025 | M51: =IF(K51="APLICA",H51*L51,0) -> 0 | N51: compras | O51: =VLOOKUP(N51,RETEICAJULIO2025,3,FALSE) -> 498000 | P51: =IF($P$3>=H51,"NO APLICA","APLICA") -> NO APLICA | Q51: =VLOOKUP(N51,RETEICAJULIO2025,4,FALSE) -> 0.006 | R51: =IF(P51="APLICA",H51*Q51,0) -> 0 | S51: =G51-(R51+M51) -> 80000 | U51: =G51-S51 -> 0
B52: SISCONT LIMITADA | C52: 814000143-8 | E52: 45860 | F52: 11E10039 | G52: 2448685 | H52: 2057718.5 | I52: Compras generales (declarantes) | J52: =VLOOKUP(I52,retfuente4[#All],3,FALSE) -> 498000 | K52: =IF(J52>=H52,"NO APLICA","APLICA") -> APLICA | L52: =VLOOKUP(I52,retfuente4[#All],4,FALSE) -> 0.025 | M52: =IF(K52="APLICA",H52*L52,0) -> 51442.962 | N52: compras | O52: =VLOOKUP(N52,RETEICAJULIO2025,3,FALSE) -> 498000 | P52: =IF($P$3>=H52,"NO APLICA","APLICA") -> APLICA | Q52: =VLOOKUP(N52,RETEICAJULIO2025,4,FALSE) -> 0.006 | R52: =IF(P52="APLICA",H52*Q52,0) -> 12346.311 | S52: =G52-(R52+M52) -> 2384895.7 | U52: =G52-S52 -> 63789.273
B53: ACEROS DUVAN | C53: 1126456991 | D53: HORMIGA | E53: 45862 | F53: 9703 | G53: 28000 | H53: 23529 | I53: Compras generales (declarantes) | J53: =VLOOKUP(I53,retfuente4[#All],3,FALSE) -> 498000 | K53: =IF(J53>=H53,"NO APLICA","APLICA") -> NO APLICA | L53: =VLOOKUP(I53,retfuente4[#All],4,FALSE) -> 0.025 | M53: =IF(K53="APLICA",H53*L53,0) -> 0 | N53: compras | O53: =VLOOKUP(N53,RETEICAJULIO2025,3,FALSE) -> 498000 | P53: =IF($P$3>=H53,"NO APLICA","APLICA") -> NO APLICA | Q53: =VLOOKUP(N53,RETEICAJULIO2025,4,FALSE) -> 0.006 | R53: =IF(P53="APLICA",H53*Q53,0) -> 0 | S53: =G53-(R53+M53) -> 28000 | U53: =G53-S53 -> 0
B54: CERAMICAS BENAVIDES | C54: 1127071533-1 | D54: OLIMPICO | E54: 45863 | F54: FECB1577 | G54: 36448432 | H54: 31286207 | I54: Compras generales (declarantes) | J54: =VLOOKUP(I54,retfuente4[#All],3,FALSE) -> 498000 | K54: =IF(J54>=H54,"NO APLICA","APLICA") -> APLICA | L54: =VLOOKUP(I54,retfuente4[#All],4,FALSE) -> 0.025 | M54: =IF(K54="APLICA",H54*L54,0) -> 782155.18 | N54: compras | O54: =VLOOKUP(N54,RETEICAJULIO2025,3,FALSE) -> 498000 | P54: =IF($P$3>=H54,"NO APLICA","APLICA") -> APLICA | Q54: =VLOOKUP(N54,RETEICAJULIO2025,4,FALSE) -> 0.006 | R54: =IF(P54="APLICA",H54*Q54,0) -> 187717.24 | S54: =G54-(R54+M54) -> 35478559 | U54: =G54-S54 -> 969872.43
B55: ACEROS DUVAN | C55: 1126456991 | D55: HORMIGA | E55: 45863 | F55: 12435 | G55: 8470235 | H55: 7270588 | I55: Compras generales (declarantes) | J55: =VLOOKUP(I55,retfuente4[#All],3,FALSE) -> 498000 | K55: =IF(J55>=H55,"NO APLICA","APLICA") -> APLICA | L55: =VLOOKUP(I55,retfuente4[#All],4,FALSE) -> 0.025 | M55: =IF(K55="APLICA",H55*L55,0) -> 181764.7 | N55: compras | O55: =VLOOKUP(N55,RETEICAJULIO2025,3,FALSE) -> 498000 | P55: =IF($P$3>=H55,"NO APLICA","APLICA") -> APLICA | Q55: =VLOOKUP(N55,RETEICAJULIO2025,4,FALSE) -> 0.006 | R55: =IF(P55="APLICA",H55*Q55,0) -> 43623.528 | S55: =G55-(R55+M55) -> 8244846.8 | U55: =G55-S55 -> 225388.23
B56: ACEROS DUVAN | C56: 1126456991 | D56: HORMIGA | E56: 45863 | F56: 7406 | G56: 83000 | H56: 69748 | I56: Compras generales (declarantes) | J56: =VLOOKUP(I56,retfuente4[#All],3,FALSE) -> 498000 | K56: =IF(J56>=H56,"NO APLICA","APLICA") -> NO APLICA | L56: =VLOOKUP(I56,retfuente4[#All],4,FALSE) -> 0.025 | M56: =IF(K56="APLICA",H56*L56,0) -> 0 | N56: compras | O56: =VLOOKUP(N56,RETEICAJULIO2025,3,FALSE) -> 498000 | P56: =IF($P$3>=H56,"NO APLICA","APLICA") -> NO APLICA | Q56: =VLOOKUP(N56,RETEICAJULIO2025,4,FALSE) -> 0.006 | R56: =IF(P56="APLICA",H56*Q56,0) -> 0 | S56: =G56-(R56+M56) -> 83000 | U56: =G56-S56 -> 0
B57: SISCONT LIMITADA | C57: 814000143-8 | E57: 45866 | F57: 11E10116 | G57: 1365872 | H57: 1147791.6 | I57: Compras generales (declarantes) | J57: =VLOOKUP(I57,retfuente4[#All],3,FALSE) -> 498000 | K57: =IF(J57>=H57,"NO APLICA","APLICA") -> APLICA | L57: =VLOOKUP(I57,retfuente4[#All],4,FALSE) -> 0.025 | M57: =IF(K57="APLICA",H57*L57,0) -> 28694.79 | N57: compras | O57: =VLOOKUP(N57,RETEICAJULIO2025,3,FALSE) -> 498000 | P57: =IF($P$3>=H57,"NO APLICA","APLICA") -> APLICA | Q57: =VLOOKUP(N57,RETEICAJULIO2025,4,FALSE) -> 0.006 | R57: =IF(P57="APLICA",H57*Q57,0) -> 6886.7496 | S57: =G57-(R57+M57) -> 1330290.5 | U57: =G57-S57 -> 35581.54
B58: CONSTRUCERAMICAS | C58: 901240065-6 | E58: 45867 | F58: 12416 | G58: 9392700 | H58: 7893025.2 | I58: Compras generales (declarantes) | J58: =VLOOKUP(I58,retfuente4[#All],3,FALSE) -> 498000 | K58: =IF(J58>=H58,"NO APLICA","APLICA") -> APLICA | L58: =VLOOKUP(I58,retfuente4[#All],4,FALSE) -> 0.025 | M58: =IF(K58="APLICA",H58*L58,0) -> 197325.63 | N58: compras | O58: =VLOOKUP(N58,RETEICAJULIO2025,3,FALSE) -> 498000 | P58: =IF($P$3>=H58,"NO APLICA","APLICA") -> APLICA | Q58: =VLOOKUP(N58,RETEICAJULIO2025,4,FALSE) -> 0.006 | R58: =IF(P58="APLICA",H58*Q58,0) -> 47358.151 | S58: =G58-(R58+M58) -> 9148016.2 | U58: =G58-S58 -> 244683.78
B59: CERAMICAS BENAVIDES | C59: 1127071533-1 | D59: OLIMPICO | E59: 45867 | F59: FECB1589 | G59: 130000 | H59: 109243.7 | I59: Compras generales (declarantes) | J59: =VLOOKUP(I59,retfuente4[#All],3,FALSE) -> 498000 | K59: =IF(J59>=H59,"NO APLICA","APLICA") -> NO APLICA | L59: =VLOOKUP(I59,retfuente4[#All],4,FALSE) -> 0.025 | M59: =IF(K59="APLICA",H59*L59,0) -> 0 | N59: compras | O59: =VLOOKUP(N59,RETEICAJULIO2025,3,FALSE) -> 498000 | P59: =IF($P$3>=H59,"NO APLICA","APLICA") -> NO APLICA | Q59: =VLOOKUP(N59,RETEICAJULIO2025,4,FALSE) -> 0.006 | R59: =IF(P59="APLICA",H59*Q59,0) -> 0 | S59: =G59-(R59+M59) -> 130000 | U59: =G59-S59 -> 0
B60: ACEROS DUVAN | C60: 1126456991 | D60: HORMIGA | E60: 45867 | F60: 12519 | G60: 60200 | H60: 50588 | I60: Compras generales (declarantes) | J60: =VLOOKUP(I60,retfuente4[#All],3,FALSE) -> 498000 | K60: =IF(J60>=H60,"NO APLICA","APLICA") -> NO APLICA | L60: =VLOOKUP(I60,retfuente4[#All],4,FALSE) -> 0.025 | M60: =IF(K60="APLICA",H60*L60,0) -> 0 | N60: compras | O60: =VLOOKUP(N60,RETEICAJULIO2025,3,FALSE) -> 498000 | P60: =IF($P$3>=H60,"NO APLICA","APLICA") -> NO APLICA | Q60: =VLOOKUP(N60,RETEICAJULIO2025,4,FALSE) -> 0.006 | R60: =IF(P60="APLICA",H60*Q60,0) -> 0 | S60: =G60-(R60+M60) -> 60200 | U60: =G60-S60 -> 0
B61: ACEROS DUVAN | C61: 1126456991 | D61: HORMIGA | E61: 45867 | F61: 12528 | G61: 308000 | H61: 258824 | I61: Compras generales (declarantes) | J61: =VLOOKUP(I61,retfuente4[#All],3,FALSE) -> 498000 | K61: =IF(J61>=H61,"NO APLICA","APLICA") -> NO APLICA | L61: =VLOOKUP(I61,retfuente4[#All],4,FALSE) -> 0.025 | M61: =IF(K61="APLICA",H61*L61,0) -> 0 | N61: compras | O61: =VLOOKUP(N61,RETEICAJULIO2025,3,FALSE) -> 498000 | P61: =IF($P$3>=H61,"NO APLICA","APLICA") -> NO APLICA | Q61: =VLOOKUP(N61,RETEICAJULIO2025,4,FALSE) -> 0.006 | R61: =IF(P61="APLICA",H61*Q61,0) -> 0 | S61: =G61-(R61+M61) -> 308000 | U61: =G61-S61 -> 0
B62: ACEROS DUVAN | C62: 1126456991 | D62: HORMIGA | E62: 45867 | F62: 9824 | G62: 47000 | H62: 39496 | I62: Compras generales (declarantes) | J62: =VLOOKUP(I62,retfuente4[#All],3,FALSE) -> 498000 | K62: =IF(J62>=H62,"NO APLICA","APLICA") -> NO APLICA | L62: =VLOOKUP(I62,retfuente4[#All],4,FALSE) -> 0.025 | M62: =IF(K62="APLICA",H62*L62,0) -> 0 | N62: compras | O62: =VLOOKUP(N62,RETEICAJULIO2025,3,FALSE) -> 498000 | P62: =IF($P$3>=H62,"NO APLICA","APLICA") -> NO APLICA | Q62: =VLOOKUP(N62,RETEICAJULIO2025,4,FALSE) -> 0.006 | R62: =IF(P62="APLICA",H62*Q62,0) -> 0 | S62: =G62-(R62+M62) -> 47000 | U62: =G62-S62 -> 0
B63: ACEROS DUVAN | C63: 1126456991 | D63: HORMIGA | E63: 45867 | F63: 9819 | G63: 770956 | H63: 661765 | I63: Compras generales (declarantes) | J63: =VLOOKUP(I63,retfuente4[#All],3,FALSE) -> 498000 | K63: =IF(J63>=H63,"NO APLICA","APLICA") -> APLICA | L63: =VLOOKUP(I63,retfuente4[#All],4,FALSE) -> 0.025 | M63: =IF(K63="APLICA",H63*L63,0) -> 16544.125 | N63: compras | O63: =VLOOKUP(N63,RETEICAJULIO2025,3,FALSE) -> 498000 | P63: =IF($P$3>=H63,"NO APLICA","APLICA") -> APLICA | Q63: =VLOOKUP(N63,RETEICAJULIO2025,4,FALSE) -> 0.006 | R63: =IF(P63="APLICA",H63*Q63,0) -> 3970.59 | S63: =G63-(R63+M63) -> 750441.29 | U63: =G63-S63 -> 20514.715
B64: ACEROS DUVAN | C64: 1126456991 | D64: HORMIGA | E64: 45869 | F64: 12632 | G64: 6617983 | H64: 5680672 | I64: Compras generales (declarantes) | J64: =VLOOKUP(I64,retfuente4[#All],3,FALSE) -> 498000 | K64: =IF(J64>=H64,"NO APLICA","APLICA") -> APLICA | L64: =VLOOKUP(I64,retfuente4[#All],4,FALSE) -> 0.025 | M64: =IF(K64="APLICA",H64*L64,0) -> 142016.8 | N64: compras | O64: =VLOOKUP(N64,RETEICAJULIO2025,3,FALSE) -> 498000 | P64: =IF($P$3>=H64,"NO APLICA","APLICA") -> APLICA | Q64: =VLOOKUP(N64,RETEICAJULIO2025,4,FALSE) -> 0.006 | R64: =IF(P64="APLICA",H64*Q64,0) -> 34084.032 | S64: =G64-(R64+M64) -> 6441882.2 | U64: =G64-S64 -> 176100.83
B65: El Constructor | C65: 1124848579 | E65: 45895 | F65: FECM132462 | G65: 127980 | H65: 107546.22 | I65: Compras generales (declarantes) | J65: =VLOOKUP(I65,retfuente4[#All],3,FALSE) -> 498000 | K65: =IF(J65>=H65,"NO APLICA","APLICA") -> NO APLICA | L65: =VLOOKUP(I65,retfuente4[#All],4,FALSE) -> 0.025 | M65: =IF(K65="APLICA",H65*L65,0) -> 0 | N65: compras | O65: =VLOOKUP(N65,RETEICAJULIO2025,3,FALSE) -> 498000 | P65: =IF($P$3>=H65,"NO APLICA","APLICA") -> NO APLICA | Q65: =VLOOKUP(N65,RETEICAJULIO2025,4,FALSE) -> 0.006 | R65: =IF(P65="APLICA",H65*Q65,0) -> 0 | S65: =G65-(R65+M65) -> 127980 | U65: =G65-S65 -> 0
B66: El Constructor | C66: 1124848579 | E66: 45895 | F66: FECM132467 | G66: 166000 | H66: 139495.8 | I66: Compras generales (declarantes) | J66: =VLOOKUP(I66,retfuente4[#All],3,FALSE) -> 498000 | K66: =IF(J66>=H66,"NO APLICA","APLICA") -> NO APLICA | L66: =VLOOKUP(I66,retfuente4[#All],4,FALSE) -> 0.025 | M66: =IF(K66="APLICA",H66*L66,0) -> 0 | N66: compras | O66: =VLOOKUP(N66,RETEICAJULIO2025,3,FALSE) -> 498000 | P66: =IF($P$3>=H66,"NO APLICA","APLICA") -> NO APLICA | Q66: =VLOOKUP(N66,RETEICAJULIO2025,4,FALSE) -> 0.006 | R66: =IF(P66="APLICA",H66*Q66,0) -> 0 | S66: =G66-(R66+M66) -> 166000 | U66: =G66-S66 -> 0
B67: El Constructor | C67: 1124848579 | E67: 45898 | F67: FECM132935 | G67: 28500 | H67: 23949.58 | I67: Compras generales (declarantes) | J67: =VLOOKUP(I67,retfuente4[#All],3,FALSE) -> 498000 | K67: =IF(J67>=H67,"NO APLICA","APLICA") -> NO APLICA | L67: =VLOOKUP(I67,retfuente4[#All],4,FALSE) -> 0.025 | M67: =IF(K67="APLICA",H67*L67,0) -> 0 | N67: compras | O67: =VLOOKUP(N67,RETEICAJULIO2025,3,FALSE) -> 498000 | P67: =IF($P$3>=H67,"NO APLICA","APLICA") -> NO APLICA | Q67: =VLOOKUP(N67,RETEICAJULIO2025,4,FALSE) -> 0.006 | R67: =IF(P67="APLICA",H67*Q67,0) -> 0 | S67: =G67-(R67+M67) -> 28500 | U67: =G67-S67 -> 0
B68: El Constructor | C68: 1124848579 | E68: 45888 | F68: FECM131490 | G68: 7140000 | H68: 6000000 | I68: Compras generales (declarantes) | J68: =VLOOKUP(I68,retfuente4[#All],3,FALSE) -> 498000 | K68: =IF(J68>=H68,"NO APLICA","APLICA") -> APLICA | L68: =VLOOKUP(I68,retfuente4[#All],4,FALSE) -> 0.025 | M68: =IF(K68="APLICA",H68*L68,0) -> 150000 | N68: compras | O68: =VLOOKUP(N68,RETEICAJULIO2025,3,FALSE) -> 498000 | P68: =IF($P$3>=H68,"NO APLICA","APLICA") -> APLICA | Q68: =VLOOKUP(N68,RETEICAJULIO2025,4,FALSE) -> 0.006 | R68: =IF(P68="APLICA",H68*Q68,0) -> 36000 | S68: =G68-(R68+M68) -> 6954000 | U68: =G68-S68 -> 186000
B69: El Constructor | C69: 1124848579 | E69: 45898 | F69: FECM132975 | G69: 198100 | H69: 166470.59 | I69: Compras generales (declarantes) | J69: =VLOOKUP(I69,retfuente4[#All],3,FALSE) -> 498000 | K69: =IF(J69>=H69,"NO APLICA","APLICA") -> NO APLICA | L69: =VLOOKUP(I69,retfuente4[#All],4,FALSE) -> 0.025 | M69: =IF(K69="APLICA",H69*L69,0) -> 0 | N69: compras | O69: =VLOOKUP(N69,RETEICAJULIO2025,3,FALSE) -> 498000 | P69: =IF($P$3>=H69,"NO APLICA","APLICA") -> NO APLICA | Q69: =VLOOKUP(N69,RETEICAJULIO2025,4,FALSE) -> 0.006 | R69: =IF(P69="APLICA",H69*Q69,0) -> 0 | S69: =G69-(R69+M69) -> 198100 | U69: =G69-S69 -> 0
B70: FERRECENTRO MUNDIAL S.A.S ZOMAC | C70: 901262650 | E70: 45898 | F70: FECO158867 | G70: 4645400 | H70: 3903697.5 | I70: Compras generales (declarantes) | J70: =VLOOKUP(I70,retfuente4[#All],3,FALSE) -> 498000 | K70: =IF(J70>=H70,"NO APLICA","APLICA") -> APLICA | L70: =VLOOKUP(I70,retfuente4[#All],4,FALSE) -> 0.025 | M70: =IF(K70="APLICA",H70*L70,0) -> 97592.437 | N70: compras | O70: =VLOOKUP(N70,RETEICAJULIO2025,3,FALSE) -> 498000 | P70: =IF($P$3>=H70,"NO APLICA","APLICA") -> APLICA | Q70: =VLOOKUP(N70,RETEICAJULIO2025,4,FALSE) -> 0.006 | R70: =IF(P70="APLICA",H70*Q70,0) -> 23422.185 | S70: =G70-(R70+M70) -> 4524385.4 | U70: =G70-S70 -> 121014.62
B71: GERARDO QUINTERO AGUIRRE | C71: 18102064 | E71: 45877 | F71: FE23159 | G71: 39000 | H71: 32773.11 | I71: Compras generales (declarantes) | J71: =VLOOKUP(I71,retfuente4[#All],3,FALSE) -> 498000 | K71: =IF(J71>=H71,"NO APLICA","APLICA") -> NO APLICA | L71: =VLOOKUP(I71,retfuente4[#All],4,FALSE) -> 0.025 | M71: =IF(K71="APLICA",H71*L71,0) -> 0 | N71: compras | O71: =VLOOKUP(N71,RETEICAJULIO2025,3,FALSE) -> 498000 | P71: =IF($P$3>=H71,"NO APLICA","APLICA") -> NO APLICA | Q71: =VLOOKUP(N71,RETEICAJULIO2025,4,FALSE) -> 0.006 | R71: =IF(P71="APLICA",H71*Q71,0) -> 0 | S71: =G71-(R71+M71) -> 39000 | U71: =G71-S71 -> 0
B72: SISCONT LIMITADA | C72: 814000143 | E72: 45877 | F72: 01E1361 | G72: 245250 | H72: 206092.44 | I72: Compras generales (declarantes) | J72: =VLOOKUP(I72,retfuente4[#All],3,FALSE) -> 498000 | K72: =IF(J72>=H72,"NO APLICA","APLICA") -> NO APLICA | L72: =VLOOKUP(I72,retfuente4[#All],4,FALSE) -> 0.025 | M72: =IF(K72="APLICA",H72*L72,0) -> 0 | N72: compras | O72: =VLOOKUP(N72,RETEICAJULIO2025,3,FALSE) -> 498000 | P72: =IF($P$3>=H72,"NO APLICA","APLICA") -> NO APLICA | Q72: =VLOOKUP(N72,RETEICAJULIO2025,4,FALSE) -> 0.006 | R72: =IF(P72="APLICA",H72*Q72,0) -> 0 | S72: =G72-(R72+M72) -> 245250 | U72: =G72-S72 -> 0
B73: SISCONT LIMITADA | C73: 814000143 | E73: 45876 | F73: 11E10237 | G73: 4344617.5 | H73: 3651564.7 | I73: Compras generales (declarantes) | J73: =VLOOKUP(I73,retfuente4[#All],3,FALSE) -> 498000 | K73: =IF(J73>=H73,"NO APLICA","APLICA") -> APLICA | L73: =VLOOKUP(I73,retfuente4[#All],4,FALSE) -> 0.025 | M73: =IF(K73="APLICA",H73*L73,0) -> 91289.118 | N73: compras | O73: =VLOOKUP(N73,RETEICAJULIO2025,3,FALSE) -> 498000 | P73: =IF($P$3>=H73,"NO APLICA","APLICA") -> APLICA | Q73: =VLOOKUP(N73,RETEICAJULIO2025,4,FALSE) -> 0.006 | R73: =IF(P73="APLICA",H73*Q73,0) -> 21909.388 | S73: =G73-(R73+M73) -> 4231419 | U73: =G73-S73 -> 113198.51
B74: SISCONT LIMITADA | C74: 814000143 | E74: 45876 | F74: 01E47424 | G74: 345242 | H74: 290119.33 | I74: Compras generales (declarantes) | J74: =VLOOKUP(I74,retfuente4[#All],3,FALSE) -> 498000 | K74: =IF(J74>=H74,"NO APLICA","APLICA") -> NO APLICA | L74: =VLOOKUP(I74,retfuente4[#All],4,FALSE) -> 0.025 | M74: =IF(K74="APLICA",H74*L74,0) -> 0 | N74: compras | O74: =VLOOKUP(N74,RETEICAJULIO2025,3,FALSE) -> 498000 | P74: =IF($P$3>=H74,"NO APLICA","APLICA") -> NO APLICA | Q74: =VLOOKUP(N74,RETEICAJULIO2025,4,FALSE) -> 0.006 | R74: =IF(P74="APLICA",H74*Q74,0) -> 0 | S74: =G74-(R74+M74) -> 345242 | U74: =G74-S74 -> 0
B75: SISCONT LIMITADA | C75: 814000143 | E75: 45894 | F75: 11E10406 | G75: 2068068 | H75: 1741626.1 | I75: Compras generales (declarantes) | J75: =VLOOKUP(I75,retfuente4[#All],3,FALSE) -> 498000 | K75: =IF(J75>=H75,"NO APLICA","APLICA") -> APLICA | L75: =VLOOKUP(I75,retfuente4[#All],4,FALSE) -> 0.025 | M75: =IF(K75="APLICA",H75*L75,0) -> 43540.651 | N75: compras | O75: =VLOOKUP(N75,RETEICAJULIO2025,3,FALSE) -> 498000 | P75: =IF($P$3>=H75,"NO APLICA","APLICA") -> APLICA | Q75: =VLOOKUP(N75,RETEICAJULIO2025,4,FALSE) -> 0.006 | R75: =IF(P75="APLICA",H75*Q75,0) -> 10449.756 | S75: =G75-(R75+M75) -> 2014077.6 | U75: =G75-S75 -> 53990.408
B76: SISCONT LIMITADA | C76: 814000143 | E76: 45895 | F76: 11E10412 | G76: 48000 | H76: 40336.13 | I76: Compras generales (declarantes) | J76: =VLOOKUP(I76,retfuente4[#All],3,FALSE) -> 498000 | K76: =IF(J76>=H76,"NO APLICA","APLICA") -> NO APLICA | L76: =VLOOKUP(I76,retfuente4[#All],4,FALSE) -> 0.025 | M76: =IF(K76="APLICA",H76*L76,0) -> 0 | N76: compras | O76: =VLOOKUP(N76,RETEICAJULIO2025,3,FALSE) -> 498000 | P76: =IF($P$3>=H76,"NO APLICA","APLICA") -> NO APLICA | Q76: =VLOOKUP(N76,RETEICAJULIO2025,4,FALSE) -> 0.006 | R76: =IF(P76="APLICA",H76*Q76,0) -> 0 | S76: =G76-(R76+M76) -> 48000 | U76: =G76-S76 -> 0
... B101: FERRECENTRO MUNDIAL S.A.S ZOMAC | C101: 901262650 | E101: 45899 | F101: NCC 12993 | G101: 4645400 | H101: 3903697.5 | I101: Compras generales (declarantes) | J101: =VLOOKUP(I101,retfuente4[#All],3,FALSE) -> 498000 | K101: =IF(J101>=H101,"NO APLICA","APLICA") -> APLICA | L101: =VLOOKUP(I101,retfuente4[#All],4,FALSE) -> 0.025 | M101: =IF(K101="APLICA",H101*L101,0) -> 97592.437 | N101: compras | O101: =VLOOKUP(N101,RETEICAJULIO2025,3,FALSE) -> 498000 | P101: =IF($P$3>=H101,"NO APLICA","APLICA") -> APLICA | Q101: =VLOOKUP(N101,RETEICAJULIO2025,4,FALSE) -> 0.006 | R101: =IF(P101="APLICA",H101*Q101,0) -> 23422.185 | S101: =G101-(R101+M101) -> 4524385.4 | U101: =G101-S101 -> 121014.62
B102: El Constructor | C102: 1124848579 | E102: 45929 | F102: FECM137397 | G102: 690000 | H102: 579831.93 | I102: Compras generales (declarantes) | J102: =VLOOKUP(I102,retfuente4[#All],3,FALSE) -> 498000 | K102: =IF(J102>=H102,"NO APLICA","APLICA") -> APLICA | L102: =VLOOKUP(I102,retfuente4[#All],4,FALSE) -> 0.025 | M102: =IF(K102="APLICA",H102*L102,0) -> 14495.798 | N102: compras | O102: =VLOOKUP(N102,RETEICAJULIO2025,3,FALSE) -> 498000 | P102: =IF($P$3>=H102,"NO APLICA","APLICA") -> APLICA | Q102: =VLOOKUP(N102,RETEICAJULIO2025,4,FALSE) -> 0.006 | R102: =IF(P102="APLICA",H102*Q102,0) -> 3478.9916 | S102: =G102-(R102+M102) -> 672025.21 | U102: =G102-S102 -> 17974.79
B103: El Constructor | C103: 1124848579 | E103: 45929 | F103: FECM137400 | G103: 691200 | H103: 580840.34 | I103: Compras generales (declarantes) | J103: =VLOOKUP(I103,retfuente4[#All],3,FALSE) -> 498000 | K103: =IF(J103>=H103,"NO APLICA","APLICA") -> APLICA | L103: =VLOOKUP(I103,retfuente4[#All],4,FALSE) -> 0.025 | M103: =IF(K103="APLICA",H103*L103,0) -> 14521.008 | N103: compras | O103: =VLOOKUP(N103,RETEICAJULIO2025,3,FALSE) -> 498000 | P103: =IF($P$3>=H103,"NO APLICA","APLICA") -> APLICA | Q103: =VLOOKUP(N103,RETEICAJULIO2025,4,FALSE) -> 0.006 | R103: =IF(P103="APLICA",H103*Q103,0) -> 3485.042 | S103: =G103-(R103+M103) -> 673193.95 | U103: =G103-S103 -> 18006.051
B104: El Constructor | C104: 1124848579 | E104: 45910 | F104: FECM134635 | G104: 1035000 | H104: 869747.9 | I104: Compras generales (declarantes) | J104: =VLOOKUP(I104,retfuente4[#All],3,FALSE) -> 498000 | K104: =IF(J104>=H104,"NO APLICA","APLICA") -> APLICA | L104: =VLOOKUP(I104,retfuente4[#All],4,FALSE) -> 0.025 | M104: =IF(K104="APLICA",H104*L104,0) -> 21743.698 | N104: compras | O104: =VLOOKUP(N104,RETEICAJULIO2025,3,FALSE) -> 498000 | P104: =IF($P$3>=H104,"NO APLICA","APLICA") -> APLICA | Q104: =VLOOKUP(N104,RETEICAJULIO2025,4,FALSE) -> 0.006 | R104: =IF(P104="APLICA",H104*Q104,0) -> 5218.4874 | S104: =G104-(R104+M104) -> 1008037.8 | U104: =G104-S104 -> 26962.185
B105: FERRECENTRO MUNDIAL S.A.S ZOMAC | C105: 901262650 | E105: 45911 | F105: FECO159712 | G105: 250400 | H105: 210420.17 | I105: Compras generales (declarantes) | J105: =VLOOKUP(I105,retfuente4[#All],3,FALSE) -> 498000 | K105: =IF(J105>=H105,"NO APLICA","APLICA") -> NO APLICA | L105: =VLOOKUP(I105,retfuente4[#All],4,FALSE) -> 0.025 | M105: =IF(K105="APLICA",H105*L105,0) -> 0 | N105: compras | O105: =VLOOKUP(N105,RETEICAJULIO2025,3,FALSE) -> 498000 | P105: =IF($P$3>=H105,"NO APLICA","APLICA") -> NO APLICA | Q105: =VLOOKUP(N105,RETEICAJULIO2025,4,FALSE) -> 0.006 | R105: =IF(P105="APLICA",H105*Q105,0) -> 0 | S105: =G105-(R105+M105) -> 250400 | U105: =G105-S105 -> 0
B106: FERRECENTRO MUNDIAL S.A.S ZOMAC | C106: 901262650 | E106: 45904 | F106: FECO159244 | G106: 401000 | H106: 336974.79 | I106: Compras generales (declarantes) | J106: =VLOOKUP(I106,retfuente4[#All],3,FALSE) -> 498000 | K106: =IF(J106>=H106,"NO APLICA","APLICA") -> NO APLICA | L106: =VLOOKUP(I106,retfuente4[#All],4,FALSE) -> 0.025 | M106: =IF(K106="APLICA",H106*L106,0) -> 0 | N106: compras | O106: =VLOOKUP(N106,RETEICAJULIO2025,3,FALSE) -> 498000 | P106: =IF($P$3>=H106,"NO APLICA","APLICA") -> NO APLICA | Q106: =VLOOKUP(N106,RETEICAJULIO2025,4,FALSE) -> 0.006 | R106: =IF(P106="APLICA",H106*Q106,0) -> 0 | S106: =G106-(R106+M106) -> 401000 | U106: =G106-S106 -> 0
B107: El Constructor | C107: 1124848579 | E107: 45922 | F107: FECM136401 | G107: 40800 | H107: 34285.71 | I107: Compras generales (declarantes) | J107: =VLOOKUP(I107,retfuente4[#All],3,FALSE) -> 498000 | K107: =IF(J107>=H107,"NO APLICA","APLICA") -> NO APLICA | L107: =VLOOKUP(I107,retfuente4[#All],4,FALSE) -> 0.025 | M107: =IF(K107="APLICA",H107*L107,0) -> 0 | N107: compras | O107: =VLOOKUP(N107,RETEICAJULIO2025,3,FALSE) -> 498000 | P107: =IF($P$3>=H107,"NO APLICA","APLICA") -> NO APLICA | Q107: =VLOOKUP(N107,RETEICAJULIO2025,4,FALSE) -> 0.006 | R107: =IF(P107="APLICA",H107*Q107,0) -> 0 | S107: =G107-(R107+M107) -> 40800 | U107: =G107-S107 -> 0
B108: El Constructor | C108: 1124848579 | E108: 45904 | F108: FECM133838 | G108: 720040 | H108: 605075.63 | I108: Compras generales (declarantes) | J108: =VLOOKUP(I108,retfuente4[#All],3,FALSE) -> 498000 | K108: =IF(J108>=H108,"NO APLICA","APLICA") -> APLICA | L108: =VLOOKUP(I108,retfuente4[#All],4,FALSE) -> 0.025 | M108: =IF(K108="APLICA",H108*L108,0) -> 15126.891 | N108: compras | O108: =VLOOKUP(N108,RETEICAJULIO2025,3,FALSE) -> 498000 | P108: =IF($P$3>=H108,"NO APLICA","APLICA") -> APLICA | Q108: =VLOOKUP(N108,RETEICAJULIO2025,4,FALSE) -> 0.006 | R108: =IF(P108="APLICA",H108*Q108,0) -> 3630.4538 | S108: =G108-(R108+M108) -> 701282.66 | U108: =G108-S108 -> 18757.345
B109: MAYERLINE CARLOSAMA LOPEZ | C109: 52382064 | E109: 45901 | F109: FVE80164 | G109: 530000 | H109: 445378.15 | I109: Compras generales (declarantes) | J109: =VLOOKUP(I109,retfuente4[#All],3,FALSE) -> 498000 | K109: =IF(J109>=H109,"NO APLICA","APLICA") -> NO APLICA | L109: =VLOOKUP(I109,retfuente4[#All],4,FALSE) -> 0.025 | M109: =IF(K109="APLICA",H109*L109,0) -> 0 | N109: compras | O109: =VLOOKUP(N109,RETEICAJULIO2025,3,FALSE) -> 498000 | P109: =IF($P$3>=H109,"NO APLICA","APLICA") -> NO APLICA | Q109: =VLOOKUP(N109,RETEICAJULIO2025,4,FALSE) -> 0.006 | R109: =IF(P109="APLICA",H109*Q109,0) -> 0 | S109: =G109-(R109+M109) -> 530000 | U109: =G109-S109 -> 0
B110: El Constructor | C110: 1124848579 | E110: 45926 | F110: FECM137086 | G110: 203000 | H110: 170588.24 | I110: Compras generales (declarantes) | J110: =VLOOKUP(I110,retfuente4[#All],3,FALSE) -> 498000 | K110: =IF(J110>=H110,"NO APLICA","APLICA") -> NO APLICA | L110: =VLOOKUP(I110,retfuente4[#All],4,FALSE) -> 0.025 | M110: =IF(K110="APLICA",H110*L110,0) -> 0 | N110: compras | O110: =VLOOKUP(N110,RETEICAJULIO2025,3,FALSE) -> 498000 | P110: =IF($P$3>=H110,"NO APLICA","APLICA") -> NO APLICA | Q110: =VLOOKUP(N110,RETEICAJULIO2025,4,FALSE) -> 0.006 | R110: =IF(P110="APLICA",H110*Q110,0) -> 0 | S110: =G110-(R110+M110) -> 203000 | U110: =G110-S110 -> 0
B111: El Constructor | C111: 1124848579 | E111: 45904 | F111: FECM133818 | G111: 127000 | H111: 106722.69 | I111: Compras generales (declarantes) | J111: =VLOOKUP(I111,retfuente4[#All],3,FALSE) -> 498000 | K111: =IF(J111>=H111,"NO APLICA","APLICA") -> NO APLICA | L111: =VLOOKUP(I111,retfuente4[#All],4,FALSE) -> 0.025 | M111: =IF(K111="APLICA",H111*L111,0) -> 0 | N111: compras | O111: =VLOOKUP(N111,RETEICAJULIO2025,3,FALSE) -> 498000 | P111: =IF($P$3>=H111,"NO APLICA","APLICA") -> NO APLICA | Q111: =VLOOKUP(N111,RETEICAJULIO2025,4,FALSE) -> 0.006 | R111: =IF(P111="APLICA",H111*Q111,0) -> 0 | S111: =G111-(R111+M111) -> 127000 | U111: =G111-S111 -> 0
B112: El Constructor | C112: 1124848579 | E112: 45909 | F112: FECM134548 | G112: 158000 | H112: 132773.11 | I112: Compras generales (declarantes) | J112: =VLOOKUP(I112,retfuente4[#All],3,FALSE) -> 498000 | K112: =IF(J112>=H112,"NO APLICA","APLICA") -> NO APLICA | L112: =VLOOKUP(I112,retfuente4[#All],4,FALSE) -> 0.025 | M112: =IF(K112="APLICA",H112*L112,0) -> 0 | N112: compras | O112: =VLOOKUP(N112,RETEICAJULIO2025,3,FALSE) -> 498000 | P112: =IF($P$3>=H112,"NO APLICA","APLICA") -> NO APLICA | Q112: =VLOOKUP(N112,RETEICAJULIO2025,4,FALSE) -> 0.006 | R112: =IF(P112="APLICA",H112*Q112,0) -> 0 | S112: =G112-(R112+M112) -> 158000 | U112: =G112-S112 -> 0
B113: FERREMONO SAS ZOMAC | C113: 901194403 | E113: 45908 | F113: CRE14500 | G113: 17000 | H113: 14285.71 | I113: Compras generales (declarantes) | J113: =VLOOKUP(I113,retfuente4[#All],3,FALSE) -> 498000 | K113: =IF(J113>=H113,"NO APLICA","APLICA") -> NO APLICA | L113: =VLOOKUP(I113,retfuente4[#All],4,FALSE) -> 0.025 | M113: =IF(K113="APLICA",H113*L113,0) -> 0 | N113: compras | O113: =VLOOKUP(N113,RETEICAJULIO2025,3,FALSE) -> 498000 | P113: =IF($P$3>=H113,"NO APLICA","APLICA") -> NO APLICA | Q113: =VLOOKUP(N113,RETEICAJULIO2025,4,FALSE) -> 0.006 | R113: =IF(P113="APLICA",H113*Q113,0) -> 0 | S113: =G113-(R113+M113) -> 17000 | U113: =G113-S113 -> 0
B114: El Constructor | C114: 1124848579 | E114: 45922 | F114: FECM136396 | G114: 24000 | H114: 20168.07 | I114: Compras generales (declarantes) | J114: =VLOOKUP(I114,retfuente4[#All],3,FALSE) -> 498000 | K114: =IF(J114>=H114,"NO APLICA","APLICA") -> NO APLICA | L114: =VLOOKUP(I114,retfuente4[#All],4,FALSE) -> 0.025 | M114: =IF(K114="APLICA",H114*L114,0) -> 0 | N114: compras | O114: =VLOOKUP(N114,RETEICAJULIO2025,3,FALSE) -> 498000 | P114: =IF($P$3>=H114,"NO APLICA","APLICA") -> NO APLICA | Q114: =VLOOKUP(N114,RETEICAJULIO2025,4,FALSE) -> 0.006 | R114: =IF(P114="APLICA",H114*Q114,0) -> 0 | S114: =G114-(R114+M114) -> 24000 | U114: =G114-S114 -> 0
B115: FERREMONO SAS ZOMAC | C115: 901194403 | E115: 45925 | F115: CRE14772 | G115: 199300 | H115: 167478.99 | I115: Compras generales (declarantes) | J115: =VLOOKUP(I115,retfuente4[#All],3,FALSE) -> 498000 | K115: =IF(J115>=H115,"NO APLICA","APLICA") -> NO APLICA | L115: =VLOOKUP(I115,retfuente4[#All],4,FALSE) -> 0.025 | M115: =IF(K115="APLICA",H115*L115,0) -> 0 | N115: compras | O115: =VLOOKUP(N115,RETEICAJULIO2025,3,FALSE) -> 498000 | P115: =IF($P$3>=H115,"NO APLICA","APLICA") -> NO APLICA | Q115: =VLOOKUP(N115,RETEICAJULIO2025,4,FALSE) -> 0.006 | R115: =IF(P115="APLICA",H115*Q115,0) -> 0 | S115: =G115-(R115+M115) -> 199300 | U115: =G115-S115 -> 0
B116: El Constructor | C116: 1124848579 | E116: 45910 | F116: FECM134733 | G116: 22000 | H116: 18487.39 | I116: Compras generales (declarantes) | J116: =VLOOKUP(I116,retfuente4[#All],3,FALSE) -> 498000 | K116: =IF(J116>=H116,"NO APLICA","APLICA") -> NO APLICA | L116: =VLOOKUP(I116,retfuente4[#All],4,FALSE) -> 0.025 | M116: =IF(K116="APLICA",H116*L116,0) -> 0 | N116: compras | O116: =VLOOKUP(N116,RETEICAJULIO2025,3,FALSE) -> 498000 | P116: =IF($P$3>=H116,"NO APLICA","APLICA") -> NO APLICA | Q116: =VLOOKUP(N116,RETEICAJULIO2025,4,FALSE) -> 0.006 | R116: =IF(P116="APLICA",H116*Q116,0) -> 0 | S116: =G116-(R116+M116) -> 22000 | U116: =G116-S116 -> 0
B117: MAYERLINE CARLOSAMA LOPEZ | C117: 52382064 | E117: 45922 | F117: FVE81411 | G117: 212000 | H117: 178151.26 | I117: Compras generales (declarantes) | J117: =VLOOKUP(I117,retfuente4[#All],3,FALSE) -> 498000 | K117: =IF(J117>=H117,"NO APLICA","APLICA") -> NO APLICA | L117: =VLOOKUP(I117,retfuente4[#All],4,FALSE) -> 0.025 | M117: =IF(K117="APLICA",H117*L117,0) -> 0 | N117: compras | O117: =VLOOKUP(N117,RETEICAJULIO2025,3,FALSE) -> 498000 | P117: =IF($P$3>=H117,"NO APLICA","APLICA") -> NO APLICA | Q117: =VLOOKUP(N117,RETEICAJULIO2025,4,FALSE) -> 0.006 | R117: =IF(P117="APLICA",H117*Q117,0) -> 0 | S117: =G117-(R117+M117) -> 212000 | U117: =G117-S117 -> 0
B118: FERRECENTRO MUNDIAL S.A.S ZOMAC | C118: 901262650 | E118: 45903 | F118: FECO159202 | G118: 1104700 | H118: 928319.33 | I118: Compras generales (declarantes) | J118: =VLOOKUP(I118,retfuente4[#All],3,FALSE) -> 498000 | K118: =IF(J118>=H118,"NO APLICA","APLICA") -> APLICA | L118: =VLOOKUP(I118,retfuente4[#All],4,FALSE) -> 0.025 | M118: =IF(K118="APLICA",H118*L118,0) -> 23207.983 | N118: compras | O118: =VLOOKUP(N118,RETEICAJULIO2025,3,FALSE) -> 498000 | P118: =IF($P$3>=H118,"NO APLICA","APLICA") -> APLICA | Q118: =VLOOKUP(N118,RETEICAJULIO2025,4,FALSE) -> 0.006 | R118: =IF(P118="APLICA",H118*Q118,0) -> 5569.916 | S118: =G118-(R118+M118) -> 1075922.1 | U118: =G118-S118 -> 28777.899
B119: El Constructor | C119: 1124848579 | E119: 45916 | F119: FECM135612 | G119: 690000 | H119: 579831.93 | I119: Compras generales (declarantes) | J119: =VLOOKUP(I119,retfuente4[#All],3,FALSE) -> 498000 | K119: =IF(J119>=H119,"NO APLICA","APLICA") -> APLICA | L119: =VLOOKUP(I119,retfuente4[#All],4,FALSE) -> 0.025 | M119: =IF(K119="APLICA",H119*L119,0) -> 14495.798 | N119: compras | O119: =VLOOKUP(N119,RETEICAJULIO2025,3,FALSE) -> 498000 | P119: =IF($P$3>=H119,"NO APLICA","APLICA") -> APLICA | Q119: =VLOOKUP(N119,RETEICAJULIO2025,4,FALSE) -> 0.006 | R119: =IF(P119="APLICA",H119*Q119,0) -> 3478.9916 | S119: =G119-(R119+M119) -> 672025.21 | U119: =G119-S119 -> 17974.79
B120: El Constructor | C120: 1124848579 | E120: 45904 | F120: FECM133802 | G120: 77000 | H120: 64705.88 | I120: Compras generales (declarantes) | J120: =VLOOKUP(I120,retfuente4[#All],3,FALSE) -> 498000 | K120: =IF(J120>=H120,"NO APLICA","APLICA") -> NO APLICA | L120: =VLOOKUP(I120,retfuente4[#All],4,FALSE) -> 0.025 | M120: =IF(K120="APLICA",H120*L120,0) -> 0 | N120: compras | O120: =VLOOKUP(N120,RETEICAJULIO2025,3,FALSE) -> 498000 | P120: =IF($P$3>=H120,"NO APLICA","APLICA") -> NO APLICA | Q120: =VLOOKUP(N120,RETEICAJULIO2025,4,FALSE) -> 0.006 | R120: =IF(P120="APLICA",H120*Q120,0) -> 0 | S120: =G120-(R120+M120) -> 77000 | U120: =G120-S120 -> 0
B121: El Constructor | C121: 1124848579 | E121: 45904 | F121: DMC3390 | G121: 77000 | H121: 64705.88 | I121: Compras generales (declarantes) | J121: =VLOOKUP(I121,retfuente4[#All],3,FALSE) -> 498000 | K121: =IF(J121>=H121,"NO APLICA","APLICA") -> NO APLICA | L121: =VLOOKUP(I121,retfuente4[#All],4,FALSE) -> 0.025 | M121: =IF(K121="APLICA",H121*L121,0) -> 0 | N121: compras | O121: =VLOOKUP(N121,RETEICAJULIO2025,3,FALSE) -> 498000 | P121: =IF($P$3>=H121,"NO APLICA","APLICA") -> NO APLICA | Q121: =VLOOKUP(N121,RETEICAJULIO2025,4,FALSE) -> 0.006 | R121: =IF(P121="APLICA",H121*Q121,0) -> 0 | S121: =G121-(R121+M121) -> 77000 | U121: =G121-S121 -> 0
... B184: FERREMONO SAS ZOMAC | C184: 901194403 | E184: 45905 | F184: CRE14444 | G184: 8500 | H184: 7142.86 | I184: Compras generales (declarantes) | J184: =VLOOKUP(I184,retfuente4[#All],3,FALSE) -> 498000 | K184: =IF(J184>=H184,"NO APLICA","APLICA") -> NO APLICA | L184: =VLOOKUP(I184,retfuente4[#All],4,FALSE) -> 0.025 | M184: =IF(K184="APLICA",H184*L184,0) -> 0 | N184: compras | O184: =VLOOKUP(N184,RETEICAJULIO2025,3,FALSE) -> 498000 | P184: =IF($P$3>=H184,"NO APLICA","APLICA") -> NO APLICA | Q184: =VLOOKUP(N184,RETEICAJULIO2025,4,FALSE) -> 0.006 | R184: =IF(P184="APLICA",H184*Q184,0) -> 0 | S184: =G184-(R184+M184) -> 8500 | U184: =G184-S184 -> 0
B185: TOTALES | G185: =SUBTOTAL(109,Tabla36[Monto Factura]) -> 2.7907776e+08 | H185: =SUBTOTAL(109,Tabla36[Base Imponible]) -> 2.3621505e+08 | M185: =SUBTOTAL(109,Tabla36[VALOR DE RETENCION]) -> 5355514.7 | R185: =SUBTOTAL(109,Tabla36[VALOR DE RETE ICA]) -> 1349193.9 | S185: =SUBTOTAL(109,Tabla36[Monto a cancelar en Caja]) -> 2.7237305e+08 | U185: =SUBTOTAL(109,Tabla36[Impuesto por factura]) -> 6704708.6

Sheet INDICADORES
B1: MALAQUITA INGENIERIA SAS
B2: NIT: 901810338-8
B3: ESTADOS FINANCIEROS A 31 DE DICIEMBRE
B5: ACTIVOS | E5: Año 1 | F5: Año 2024
C6: Activo Corriente
D7: Efectivo y equivalentes de efectivo
D8: Cuentas comerciales y otras cuentas por cobrar
D9: Inventarios
D10: Productos terminados
D11: Materias Primas y Productos en proceso | E11: 1.4769411e+08 | F11: 1.4769411e+08
D12: Materiales y respuestos
D13: Materiales en transito
D14: Inversiones
C15: Total Activos Corrientes | E15: =SUM(E6:E14) -> 1.4769411e+08 | F15: =SUM(F6:F14) -> 1.4769411e+08
C16: Activos No Corrientes
D17: Propiedad planta y equipos
D18: Propiedades de Inversiones
D19: Prestamos a empleados
D20: Inversiones
D21: Otros activos
C22: Total Activos No Corrientes | E22: =SUM(E17:E21) -> 0 | F22: =SUM(F17:F21) -> 0
C23: Total Activos | E23: =SUM(E22+E15) -> 1.4769411e+08 | F23: =SUM(F22+F15) -> 1.4769411e+08
B25: PASIVOS
C26: Pasivos Corrientes
D27: Obligaciones financieras | E27: 634152.41 | F27: 634152.41
D28: Proveedores
D29: Beneficios a empleados | E29: 900000 | F29: 900000
D30: Impuesto de renta | E30: 2951482.4 | F30: 2951482.4
D31: Dividendos por pagar
D32: Ingresos diferidos
D33: Gastos de Intereses | E33: 0 | F33: 0
C34: Total Pasivos Corrientes | E34: =SUM(E27:E33) -> 4485634.8 | F34: =SUM(F27:F33) -> 4485634.8
C35: Pasivos No Corrientes
D36: Obligaciones financieras
D37: Beneficios a empleados
D38: Impuesto de renta diferido
D39: otras provisiones
C40: Total Pasivo No Corriente | E40: =SUM(E36:E39) -> 0 | F40: =SUM(F36:F39) -> 0
C41: Total Pasivos | E41: =SUM(E40+E34) -> 4485634.8 | F41: =SUM(F40+F34) -> 4485634.8
B43: PATRIMONIO
D44: Capital Social | E44: 50000000 | F44: 50000000
D45: Ingresos de ventas | E45: 250000000 | F45: 230000000
C46: Total Patrimonio | E46: =SUM(E44:E45) -> 300000000 | F46: =SUM(F42:F45) -> 280000000
B49: Utilidad Bruta | D49: Ingresos-Activo Corriente | E49: =E45-E15 -> 1.0230589e+08 | F49: =F45-F15 -> 82305889
B50: Gastos Operativos | D50: Pasivos corrientes | E50: =E34 -> 4485634.8 | F50: =F34 -> 4485634.8
B51: Utilidad Operacional | D51: Utilidad Bruta-Gastos Operativos | E51: =E49-E50 -> 97820254 | F51: =F49-F50 -> 77820254
B52: Gastos de Intereses | D52: Intereses Anuales | E52: 0 | F52: 0
B53: Indice de Liquidez | D53: Activo Corriente/Päsivo Corriente | E53: =E15/E34 -> 32.926022 | F53: =F15/F34 -> 32.926022
B54: Indice de Endeudamiento | D54: Pasivo total/Activo total | E54: =E41/E23 -> 0.030371115 | F54: =F41/F23 -> 0.030371115
B55: Razon de cobertura de Intereses | D55: Utilidad Operacional/Gastos de intereses | E55: 0 | F55: 0
B56: Rentabilidad del patrimonio | D56: utilidad operacional/patrimonio | E56: =E51/E46 -> 0.32606751 | F56: =F51/F46 -> 0.27792948
B57: Rentabilidad del activo | D57: utilidad operacional/activo total | E57: =E51/E23 -> 0.66231655 | F57: =F51/F23 -> 0.52690153
B58: Indice de Endeudamiento | D58: Pasivo total/Activo total | E58: =E41/E23 -> 0.030371115 | F58: =F41/F23 -> 0.030371115
